Comparator_8bits.v
module Comparator_8bits(Max, Min, A, B/*, clk*/);
    //input             clk;
    input       [7:0] A, B;
    output      [7:0] Max, Min;

    // always @(posedge clk) begin
    //     Max <= (A > B) ? A : B;
    //     Min <= (A < B) ? A : B;
    // end

    assign Max = (A > B) ? A : B;
    assign Min = (A < B) ? A : B;
endmodule

Ascending_Sorter_3inputs_8bits.v
//`include "Comparator_8bits.v"

module Ascending_Sorter_3inputs_8bits(min, mid, max, 
                                      in0, in1, in2,
                                      clk);
    
    input   wire        clk;
    input   wire [7:0]  in0, in1, in2;
    output  reg  [7:0]  min, mid, max;

    reg [7:0] rin0, rin1, rin2;
    reg [7:0] cmp0, cmp1, cmp2;  //0: in0 < in1?; 1:in1 < in2?; in0 < in2? 

    always @(posedge clk) begin
        //STAGE 0
        rin0 <= in0;
        rin1 <= in1;
        rin2 <= in2;

        cmp0 <= (in0 < in1);
        cmp1 <= (in1 < in2);
        cmp2 <= (in0 < in2);

        //STAGE 1

        if (cmp0) begin
            if (cmp2) min <= rin0;
            else min <= rin2;

            if (cmp1) begin
                mid <= rin1;
                max <= rin2;
            end
            else begin
                mid <= rin2;
                max <= rin1;
            end
        end
        else begin
            if (cmp1) min = rin1;
            else min = rin2;

            if (cmp2) begin
                mid <= rin0;
                max <= rin2;
            end
            else begin
                mid <= rin2;
                max <= rin0;
            end
        end

    end


    // always@(posedge clk) begin
    //     min <= (in0 < in1) ? ((in0 < in2) ? in0 : in2) : ((in1 < in2) ? in1 : in2);
    //     max <= (in0 > in1) ? ((in0 > in2) ? in0 : in2) : ((in1 > in2) ? in1 : in2);
    //     mid <= (in0 > in1) ? 
    //            ((in1 > in2) ? in1 : ((in0 > in2) ? in2 : in0)) : 
    //            ((in0 > in2) ? in0 : ((in1 > in2) ? in2 : in1));
    // end

    
endmodule

tb_Ascending_Sorter_3inputs_8bits.v
`timescale 1ns / 1ps
`include "Ascending_Sorter_3inputs_8bits.v"

module tb_Ascending_Sorter_3inputs_8bits;

    reg clk;
    reg [7:0] in0, in1, in2;
    wire [7:0] min, mid, max;

    Ascending_Sorter_3inputs_8bits uut (
        .min(min),
        .mid(mid),
        .max(max),
        .in0(in0),
        .in1(in1),
        .in2(in2),
        .clk(clk)
    );

    initial begin
        clk = 0;
        forever #5 clk = ~clk;
    end

    initial begin
        $dumpfile("tb_Ascending_Sorter_3inputs_8bits.vcd");
        $dumpvars(0, tb_Ascending_Sorter_3inputs_8bits);

        in0 = 8'd0; in1 = 8'd0; in2 = 8'd0;
        #10;
        
        in0 = 8'd3; in1 = 8'd5; in2 = 8'd7;
        #10;
        
        in0 = 8'd1; in1 = 8'd2; in2 = 8'd3;
        #10;
        
        in0 = 8'd45; in1 = 8'd12; in2 = 8'd78;
        #10;
        
        in0 = 8'd55; in1 = 8'd55; in2 = 8'd55;
        #10;
        
        in0 = 8'd15; in1 = 8'd40; in2 = 8'd40;
        #10;
        
        in0 = 8'd90; in1 = 8'd30; in2 = 8'd30;
        #10;
        
        in0 = 8'd0; in1 = 8'd0; in2 = 8'd0;
        #10;
        
        in0 = 8'd255; in1 = 8'd255; in2 = 8'd255;
        #10;
        
        in0 = 8'd0; in1 = 8'd128; in2 = 8'd255;
        #10;
        
        in0 = 8'd66; in1 = 8'd22; in2 = 8'd88;
        #10;
        
        in0 = 8'd5; in1 = 8'd50; in2 = 8'd100;
        #10;
        
        in0 = 8'd7; in1 = 8'd200; in2 = 8'd77;
        #10;
        
        in0 = 8'd60; in1 = 8'd15; in2 = 8'd150;
        #10;
        
        in0 = 8'd220; in1 = 8'd33; in2 = 8'd111;
        #10;
        
        in0 = 8'd80; in1 = 8'd190; in2 = 8'd9;
        #10;
        
        in0 = 8'd240; in1 = 8'd95; in2 = 8'd1;
        #10;
        
        in0 = 8'd40; in1 = 8'd40; in2 = 8'd80;
        #10;
        
        in0 = 8'd35; in1 = 8'd99; in2 = 8'd35;
        #10;
        
        in0 = 8'd180; in1 = 8'd70; in2 = 8'd70;
        #10;
        
        in0 = 8'd125; in1 = 8'd125; in2 = 8'd20;
        #10;
        
        in0 = 8'd145; in1 = 8'd50; in2 = 8'd145;
        #10;
        
        in0 = 8'd18; in1 = 8'd200; in2 = 8'd200;
        #10;
        
        in0 = 8'd100; in1 = 8'd101; in2 = 8'd102;
        #10;
        
        in0 = 8'd2; in1 = 8'd127; in2 = 8'd250;
        #10;
        
        in0 = 8'd64; in1 = 8'd16; in2 = 8'd128;
        #10;
        
        in0 = 8'd1; in1 = 8'd2; in2 = 8'd3;
        #10;
        
        in0 = 8'd253; in1 = 8'd254; in2 = 8'd255;
        #10;
        
        in0 = 8'd120; in1 = 8'd135; in2 = 8'd128;
        #10;
        
        in0 = 8'd0; in1 = 8'd75; in2 = 8'd150;
        #10;
        
        in0 = 8'd100; in1 = 8'd255; in2 = 8'd50;
        #10;
        
        in0 = 8'd97; in1 = 8'd53; in2 = 8'd149;
        #10;
        
        in0 = 8'd89; in1 = 8'd144; in2 = 8'd55;
        #10;
        
        in0 = 8'd90; in1 = 8'd30; in2 = 8'd60;
        #10;
        
        in0 = 8'd73; in1 = 8'd29; in2 = 8'd171;
        #10;
        
        in0 = 8'd84; in1 = 8'd166; in2 = 8'd42;
        #10;
        
        #50;
        $finish;
    end
    
endmodule

tb_Ascending_Sorter_3inputs_8bits.vcd
$date
	Tue Dec 23 22:37:10 2025
$end
$version
	Icarus Verilog
$end
$timescale
	1ps
$end
$scope module tb_Ascending_Sorter_3inputs_8bits $end
$var wire 8 ! min [7:0] $end
$var wire 8 " mid [7:0] $end
$var wire 8 # max [7:0] $end
$var reg 1 $ clk $end
$var reg 8 % in0 [7:0] $end
$var reg 8 & in1 [7:0] $end
$var reg 8 ' in2 [7:0] $end
$scope module uut $end
$var wire 1 $ clk $end
$var wire 8 ( in0 [7:0] $end
$var wire 8 ) in1 [7:0] $end
$var wire 8 * in2 [7:0] $end
$var reg 8 + cmp0 [7:0] $end
$var reg 8 , cmp1 [7:0] $end
$var reg 8 - cmp2 [7:0] $end
$var reg 8 . max [7:0] $end
$var reg 8 / mid [7:0] $end
$var reg 8 0 min [7:0] $end
$var reg 8 1 rin0 [7:0] $end
$var reg 8 2 rin1 [7:0] $end
$var reg 8 3 rin2 [7:0] $end
$upscope $end
$upscope $end
$enddefinitions $end
$comment Show the parameter values. $end
$dumpall
$end
#0
$dumpvars
bx 3
bx 2
bx 1
bx 0
bx /
bx .
bx -
bx ,
bx +
b0 *
b0 )
b0 (
b0 '
b0 &
b0 %
0$
bx #
bx "
bx !
$end
#5000
b0 -
b0 ,
b0 +
b0 3
b0 2
b0 1
1$
#10000
0$
b111 '
b111 *
b101 &
b101 )
b11 %
b11 (
#15000
b0 #
b0 .
b0 "
b0 /
b1 -
b1 ,
b1 +
b111 3
b101 2
b11 1
b0 !
b0 0
1$
#20000
0$
b11 '
b11 *
b10 &
b10 )
b1 %
b1 (
#25000
b111 #
b111 .
b101 "
b101 /
b11 !
b11 0
b11 3
b10 2
b1 1
1$
#30000
0$
b1001110 '
b1001110 *
b1100 &
b1100 )
b101101 %
b101101 (
#35000
b11 #
b11 .
b10 "
b10 /
b1 !
b1 0
b0 +
b1001110 3
b1100 2
b101101 1
1$
#40000
0$
b110111 '
b110111 *
b110111 &
b110111 )
b110111 %
b110111 (
#45000
b1001110 #
b1001110 .
b101101 "
b101101 /
b0 -
b0 ,
b110111 3
b110111 2
b110111 1
b1100 !
b1100 0
1$
#50000
0$
b101000 '
b101000 *
b101000 &
b101000 )
b1111 %
b1111 (
#55000
b110111 #
b110111 .
b110111 "
b110111 /
b1 -
b1 +
b101000 3
b101000 2
b1111 1
b110111 !
b110111 0
1$
#60000
0$
b11110 '
b11110 *
b11110 &
b11110 )
b1011010 %
b1011010 (
#65000
b101000 #
b101000 .
b101000 "
b101000 /
b1111 !
b1111 0
b0 -
b0 +
b11110 3
b11110 2
b1011010 1
1$
#70000
0$
b0 '
b0 *
b0 &
b0 )
b0 %
b0 (
#75000
b1011010 #
b1011010 .
b11110 "
b11110 /
b0 3
b0 2
b0 1
b11110 !
b11110 0
1$
#80000
0$
b11111111 '
b11111111 *
b11111111 &
b11111111 )
b11111111 %
b11111111 (
#85000
b0 #
b0 .
b0 "
b0 /
b11111111 3
b11111111 2
b11111111 1
b0 !
b0 0
1$
#90000
0$
b10000000 &
b10000000 )
b0 %
b0 (
#95000
b11111111 #
b11111111 .
b11111111 "
b11111111 /
b1 -
b1 ,
b1 +
b10000000 2
b0 1
b11111111 !
b11111111 0
1$
#100000
0$
b1011000 '
b1011000 *
b10110 &
b10110 )
b1000010 %
b1000010 (
#105000
b10000000 "
b10000000 /
b0 !
b0 0
b0 +
b1011000 3
b10110 2
b1000010 1
1$
#110000
0$
b1100100 '
b1100100 *
b110010 &
b110010 )
b101 %
b101 (
#115000
b1011000 #
b1011000 .
b1000010 "
b1000010 /
b1 +
b1100100 3
b110010 2
b101 1
b10110 !
b10110 0
1$
#120000
0$
b1001101 '
b1001101 *
b11001000 &
b11001000 )
b111 %
b111 (
#125000
b1100100 #
b1100100 .
b110010 "
b110010 /
b101 !
b101 0
b0 ,
b1001101 3
b11001000 2
b111 1
1$
#130000
0$
b10010110 '
b10010110 *
b1111 &
b1111 )
b111100 %
b111100 (
#135000
b11001000 #
b11001000 .
b1001101 "
b1001101 /
b111 !
b111 0
b1 ,
b0 +
b10010110 3
b1111 2
b111100 1
1$
#140000
0$
b1101111 '
b1101111 *
b100001 &
b100001 )
b11011100 %
b11011100 (
#145000
b10010110 #
b10010110 .
b111100 "
b111100 /
b0 -
b1101111 3
b100001 2
b11011100 1
b1111 !
b1111 0
1$
#150000
0$
b1001 '
b1001 *
b10111110 &
b10111110 )
b1010000 %
b1010000 (
#155000
b11011100 #
b11011100 .
b1101111 "
b1101111 /
b0 ,
b1 +
b1001 3
b10111110 2
b1010000 1
b100001 !
b100001 0
1$
#160000
0$
b1 '
b1 *
b1011111 &
b1011111 )
b11110000 %
b11110000 (
#165000
b10111110 #
b10111110 .
b1001 "
b1001 /
b1001 !
b1001 0
b0 +
b1 3
b1011111 2
b11110000 1
1$
#170000
0$
b1010000 '
b1010000 *
b101000 &
b101000 )
b101000 %
b101000 (
#175000
b11110000 #
b11110000 .
b1 "
b1 /
b1 -
b1 ,
b1010000 3
b101000 2
b101000 1
b1 !
b1 0
1$
#180000
0$
b100011 '
b100011 *
b1100011 &
b1100011 )
b100011 %
b100011 (
#185000
b1010000 #
b1010000 .
b101000 "
b101000 /
b0 -
b0 ,
b1 +
b100011 3
b1100011 2
b100011 1
b101000 !
b101000 0
1$
#190000
0$
b1000110 '
b1000110 *
b1000110 &
b1000110 )
b10110100 %
b10110100 (
#195000
b1100011 #
b1100011 .
b100011 "
b100011 /
b100011 !
b100011 0
b0 +
b1000110 3
b1000110 2
b10110100 1
1$
#200000
0$
b10100 '
b10100 *
b1111101 &
b1111101 )
b1111101 %
b1111101 (
#205000
b10110100 #
b10110100 .
b1000110 "
b1000110 /
b10100 3
b1111101 2
b1111101 1
b1000110 !
b1000110 0
1$
#210000
0$
b10010001 '
b10010001 *
b110010 &
b110010 )
b10010001 %
b10010001 (
#215000
b1111101 #
b1111101 .
b10100 "
b10100 /
b1 ,
b10010001 3
b110010 2
b10010001 1
b10100 !
b10100 0
1$
#220000
0$
b11001000 '
b11001000 *
b11001000 &
b11001000 )
b10010 %
b10010 (
#225000
b10010001 #
b10010001 .
b10010001 "
b10010001 /
b1 -
b0 ,
b1 +
b11001000 3
b11001000 2
b10010 1
b110010 !
b110010 0
1$
#230000
0$
b1100110 '
b1100110 *
b1100101 &
b1100101 )
b1100100 %
b1100100 (
#235000
b11001000 #
b11001000 .
b11001000 "
b11001000 /
b10010 !
b10010 0
b1 ,
b1100110 3
b1100101 2
b1100100 1
1$
#240000
0$
b11111010 '
b11111010 *
b1111111 &
b1111111 )
b10 %
b10 (
#245000
b1100110 #
b1100110 .
b1100101 "
b1100101 /
b1100100 !
b1100100 0
b11111010 3
b1111111 2
b10 1
1$
#250000
0$
b10000000 '
b10000000 *
b10000 &
b10000 )
b1000000 %
b1000000 (
#255000
b11111010 #
b11111010 .
b1111111 "
b1111111 /
b10 !
b10 0
b0 +
b10000000 3
b10000 2
b1000000 1
1$
#260000
0$
b11 '
b11 *
b10 &
b10 )
b1 %
b1 (
#265000
b10000000 #
b10000000 .
b1000000 "
b1000000 /
b1 +
b11 3
b10 2
b1 1
b10000 !
b10000 0
1$
#270000
0$
b11111111 '
b11111111 *
b11111110 &
b11111110 )
b11111101 %
b11111101 (
#275000
b11 #
b11 .
b10 "
b10 /
b1 !
b1 0
b11111111 3
b11111110 2
b11111101 1
1$
#280000
0$
b10000000 '
b10000000 *
b10000111 &
b10000111 )
b1111000 %
b1111000 (
#285000
b11111111 #
b11111111 .
b11111110 "
b11111110 /
b11111101 !
b11111101 0
b0 ,
b10000000 3
b10000111 2
b1111000 1
1$
#290000
0$
b10010110 '
b10010110 *
b1001011 &
b1001011 )
b0 %
b0 (
#295000
b10000111 #
b10000111 .
b10000000 "
b10000000 /
b1111000 !
b1111000 0
b1 ,
b10010110 3
b1001011 2
b0 1
1$
#300000
0$
b110010 '
b110010 *
b11111111 &
b11111111 )
b1100100 %
b1100100 (
#305000
b10010110 #
b10010110 .
b1001011 "
b1001011 /
b0 !
b0 0
b0 -
b0 ,
b110010 3
b11111111 2
b1100100 1
1$
#310000
0$
b10010101 '
b10010101 *
b110101 &
b110101 )
b1100001 %
b1100001 (
#315000
b11111111 #
b11111111 .
b110010 "
b110010 /
b110010 !
b110010 0
b1 -
b1 ,
b0 +
b10010101 3
b110101 2
b1100001 1
1$
#320000
0$
b110111 '
b110111 *
b10010000 &
b10010000 )
b1011001 %
b1011001 (
#325000
b10010101 #
b10010101 .
b1100001 "
b1100001 /
b0 -
b0 ,
b1 +
b110111 3
b10010000 2
b1011001 1
b110101 !
b110101 0
1$
#330000
0$
b111100 '
b111100 *
b11110 &
b11110 )
b1011010 %
b1011010 (
#335000
b10010000 #
b10010000 .
b110111 "
b110111 /
b110111 !
b110111 0
b1 ,
b0 +
b111100 3
b11110 2
b1011010 1
1$
#340000
0$
b10101011 '
b10101011 *
b11101 &
b11101 )
b1001001 %
b1001001 (
#345000
b1011010 #
b1011010 .
b111100 "
b111100 /
b1 -
b10101011 3
b11101 2
b1001001 1
b11110 !
b11110 0
1$
#350000
0$
b101010 '
b101010 *
b10100110 &
b10100110 )
b1010100 %
b1010100 (
#355000
b10101011 #
b10101011 .
b1001001 "
b1001001 /
b0 -
b0 ,
b1 +
b101010 3
b10100110 2
b1010100 1
b11101 !
b11101 0
1$
#360000
0$
#365000
b10100110 #
b10100110 .
b101010 "
b101010 /
b101010 !
b101010 0
1$
