Comparator_8bits.v
module Comparator_8bits(Max, Min, A, B/*, clk*/);
    //input             clk;
    input       [7:0] A, B;
    output      [7:0] Max, Min;

    // always @(posedge clk) begin
    //     Max <= (A > B) ? A : B;
    //     Min <= (A < B) ? A : B;
    // end

    assign Max = (A > B) ? A : B;
    assign Min = (A < B) ? A : B;
endmodule

Ascending_Sorter_3inputs_8bits.v
//`include "Comparator_8bits.v"

module Ascending_Sorter_3inputs_8bits(min, mid, max, 
                                      in0, in1, in2,
                                      clk);
    
    input   wire        clk;
    input   wire [7:0]  in0, in1, in2;
    output  reg  [7:0]  min, mid, max;

    //reg     [7:0] st0_buf[2:0]; // [0] <- max, [1] <- min, [2] <- in2

    wire    [7:0] wC0_Max, wC0_Min;
    wire    [7:0] wC1_Max, wC1_Min;
    wire    [7:0] wC2_Max, wC2_Min;

    reg     [7:0] State0_Buf[2:0];
    reg     [7:0] State1_Buf[2:0];



    Comparator_8bits C0(.Max(wC0_Max), .Min(wC0_Min),
                        .A(in0), .B(in1));

    Comparator_8bits C1(.Max(wC1_Max), .Min(wC1_Min),
                        .A(State0_Buf[0]), .B(State0_Buf[2]));

    Comparator_8bits C2(.Max(wC2_Max), .Min(wC2_Min),
                        .A(State1_Buf[1]), .B(State1_Buf[2]));

    always @(posedge clk) begin
        State0_Buf[0] <= wC0_Max;
        State0_Buf[1] <= wC0_Min;
        State0_Buf[2] <= in2;

        State1_Buf[0] <= wC1_Max;
        State1_Buf[1] <= wC1_Min;
        State1_Buf[2] <= State0_Buf[1];

        max <= State1_Buf[0];
        mid <= wC2_Max;
        min <= wC2_Min;

    end


    // always@(posedge clk) begin
    //     min <= (in0 < in1) ? ((in0 < in2) ? in0 : in2) : ((in1 < in2) ? in1 : in2);
    //     max <= (in0 > in1) ? ((in0 > in2) ? in0 : in2) : ((in1 > in2) ? in1 : in2);
    //     mid <= (in0 > in1) ? 
    //            ((in1 > in2) ? in1 : ((in0 > in2) ? in2 : in0)) : 
    //            ((in0 > in2) ? in0 : ((in1 > in2) ? in2 : in1));
    // end

    
endmodule

tb_Ascending_Sorter_3inputs_8bits.v
`timescale 1ns / 1ps
`include "Ascending_Sorter_3inputs_8bits.v"

module tb_Ascending_Sorter_3inputs_8bits;

    reg clk;
    reg [7:0] in0, in1, in2;
    wire [7:0] min, mid, max;

    Ascending_Sorter_3inputs_8bits uut (
        .min(min),
        .mid(mid),
        .max(max),
        .in0(in0),
        .in1(in1),
        .in2(in2),
        .clk(clk)
    );

    initial begin
        clk = 0;
        forever #5 clk = ~clk;
    end

    initial begin
        $dumpfile("tb_Ascending_Sorter_3inputs_8bits.vcd");
        $dumpvars(0, tb_Ascending_Sorter_3inputs_8bits);

        in0 = 8'd0; in1 = 8'd0; in2 = 8'd0;
        #10;
        
        in0 = 8'd3; in1 = 8'd5; in2 = 8'd7;
        #10;
        
        in0 = 8'd1; in1 = 8'd2; in2 = 8'd3;
        #10;
        
        in0 = 8'd45; in1 = 8'd12; in2 = 8'd78;
        #10;
        
        in0 = 8'd55; in1 = 8'd55; in2 = 8'd55;
        #10;
        
        in0 = 8'd15; in1 = 8'd40; in2 = 8'd40;
        #10;
        
        in0 = 8'd90; in1 = 8'd30; in2 = 8'd30;
        #10;
        
        in0 = 8'd0; in1 = 8'd0; in2 = 8'd0;
        #10;
        
        in0 = 8'd255; in1 = 8'd255; in2 = 8'd255;
        #10;
        
        in0 = 8'd0; in1 = 8'd128; in2 = 8'd255;
        #10;
        
        in0 = 8'd66; in1 = 8'd22; in2 = 8'd88;
        #10;
        
        in0 = 8'd5; in1 = 8'd50; in2 = 8'd100;
        #10;
        
        in0 = 8'd7; in1 = 8'd200; in2 = 8'd77;
        #10;
        
        in0 = 8'd60; in1 = 8'd15; in2 = 8'd150;
        #10;
        
        in0 = 8'd220; in1 = 8'd33; in2 = 8'd111;
        #10;
        
        in0 = 8'd80; in1 = 8'd190; in2 = 8'd9;
        #10;
        
        in0 = 8'd240; in1 = 8'd95; in2 = 8'd1;
        #10;
        
        in0 = 8'd40; in1 = 8'd40; in2 = 8'd80;
        #10;
        
        in0 = 8'd35; in1 = 8'd99; in2 = 8'd35;
        #10;
        
        in0 = 8'd180; in1 = 8'd70; in2 = 8'd70;
        #10;
        
        in0 = 8'd125; in1 = 8'd125; in2 = 8'd20;
        #10;
        
        in0 = 8'd145; in1 = 8'd50; in2 = 8'd145;
        #10;
        
        in0 = 8'd18; in1 = 8'd200; in2 = 8'd200;
        #10;
        
        in0 = 8'd100; in1 = 8'd101; in2 = 8'd102;
        #10;
        
        in0 = 8'd2; in1 = 8'd127; in2 = 8'd250;
        #10;
        
        in0 = 8'd64; in1 = 8'd16; in2 = 8'd128;
        #10;
        
        in0 = 8'd1; in1 = 8'd2; in2 = 8'd3;
        #10;
        
        in0 = 8'd253; in1 = 8'd254; in2 = 8'd255;
        #10;
        
        in0 = 8'd120; in1 = 8'd135; in2 = 8'd128;
        #10;
        
        in0 = 8'd0; in1 = 8'd75; in2 = 8'd150;
        #10;
        
        in0 = 8'd100; in1 = 8'd255; in2 = 8'd50;
        #10;
        
        in0 = 8'd97; in1 = 8'd53; in2 = 8'd149;
        #10;
        
        in0 = 8'd89; in1 = 8'd144; in2 = 8'd55;
        #10;
        
        in0 = 8'd90; in1 = 8'd30; in2 = 8'd60;
        #10;
        
        in0 = 8'd73; in1 = 8'd29; in2 = 8'd171;
        #10;
        
        in0 = 8'd84; in1 = 8'd166; in2 = 8'd42;
        #10;
        
        #50;
        $finish;
    end
    
endmodule

tb_Ascending_Sorter_3inputs_8bits.vcd
$date
	Tue Dec 23 12:41:09 2025
$end
$version
	Icarus Verilog
$end
$timescale
	1ps
$end
$scope module tb_Ascending_Sorter_3inputs_8bits $end
$var wire 8 ! min [7:0] $end
$var wire 8 " mid [7:0] $end
$var wire 8 # max [7:0] $end
$var reg 1 $ clk $end
$var reg 8 % in0 [7:0] $end
$var reg 8 & in1 [7:0] $end
$var reg 8 ' in2 [7:0] $end
$scope module uut $end
$var wire 1 $ clk $end
$var wire 8 ( in0 [7:0] $end
$var wire 8 ) in1 [7:0] $end
$var wire 8 * in2 [7:0] $end
$var wire 8 + wC2_Min [7:0] $end
$var wire 8 , wC2_Max [7:0] $end
$var wire 8 - wC1_Min [7:0] $end
$var wire 8 . wC1_Max [7:0] $end
$var wire 8 / wC0_Min [7:0] $end
$var wire 8 0 wC0_Max [7:0] $end
$var reg 8 1 max [7:0] $end
$var reg 8 2 mid [7:0] $end
$var reg 8 3 min [7:0] $end
$scope module C0 $end
$var wire 8 4 A [7:0] $end
$var wire 8 5 B [7:0] $end
$var wire 8 6 Min [7:0] $end
$var wire 8 7 Max [7:0] $end
$upscope $end
$scope module C1 $end
$var wire 8 8 A [7:0] $end
$var wire 8 9 B [7:0] $end
$var wire 8 : Min [7:0] $end
$var wire 8 ; Max [7:0] $end
$upscope $end
$scope module C2 $end
$var wire 8 < A [7:0] $end
$var wire 8 = B [7:0] $end
$var wire 8 > Min [7:0] $end
$var wire 8 ? Max [7:0] $end
$upscope $end
$upscope $end
$upscope $end
$enddefinitions $end
$comment Show the parameter values. $end
$dumpall
$end
#0
$dumpvars
bx ?
bx >
bx =
bx <
bx ;
bx :
bx 9
bx 8
b0 7
b0 6
b0 5
b0 4
bx 3
bx 2
bx 1
b0 0
b0 /
bx .
bx -
bx ,
bx +
b0 *
b0 )
b0 (
b0 '
b0 &
b0 %
0$
bx #
bx "
bx !
$end
#5000
b0 .
b0 ;
b0 -
b0 :
b0 9
b0 8
1$
#10000
b11 /
b11 6
b101 0
b101 7
0$
b111 '
b111 *
b101 &
b101 )
b101 5
b11 %
b11 (
b11 4
#15000
b0 ,
b0 ?
b0 +
b0 >
b101 -
b101 :
b111 .
b111 ;
b0 =
b0 <
b111 9
b101 8
1$
#20000
b10 0
b10 7
b1 /
b1 6
0$
b11 '
b11 *
b10 &
b10 )
b10 5
b1 %
b1 (
b1 4
#25000
b11 +
b11 >
b101 ,
b101 ?
b11 .
b11 ;
b10 -
b10 :
b0 !
b0 3
b0 "
b0 2
b0 #
b0 1
b11 =
b101 <
b11 9
b10 8
1$
#30000
b101101 0
b101101 7
b1100 /
b1100 6
0$
b1001110 '
b1001110 *
b1100 &
b1100 )
b1100 5
b101101 %
b101101 (
b101101 4
#35000
b10 ,
b10 ?
b1 +
b1 >
b1001110 .
b1001110 ;
b101101 -
b101101 :
b11 !
b11 3
b101 "
b101 2
b111 #
b111 1
b1 =
b10 <
b1001110 9
b101101 8
1$
#40000
b110111 /
b110111 6
b110111 0
b110111 7
0$
b110111 '
b110111 *
b110111 &
b110111 )
b110111 5
b110111 %
b110111 (
b110111 4
#45000
b1100 +
b1100 >
b101101 ,
b101101 ?
b110111 .
b110111 ;
b110111 -
b110111 :
b1 !
b1 3
b10 "
b10 2
b11 #
b11 1
b1100 =
b101101 <
b110111 9
b110111 8
1$
#50000
b101000 0
b101000 7
b1111 /
b1111 6
0$
b101000 '
b101000 *
b101000 &
b101000 )
b101000 5
b1111 %
b1111 (
b1111 4
#55000
b110111 +
b110111 >
b110111 ,
b110111 ?
b101000 .
b101000 ;
b101000 -
b101000 :
b1100 !
b1100 3
b101101 "
b101101 2
b1001110 #
b1001110 1
b110111 =
b110111 <
b101000 9
b101000 8
1$
#60000
b1011010 0
b1011010 7
b11110 /
b11110 6
0$
b11110 '
b11110 *
b11110 &
b11110 )
b11110 5
b1011010 %
b1011010 (
b1011010 4
#65000
b101000 ,
b101000 ?
b1111 +
b1111 >
b11110 -
b11110 :
b1011010 .
b1011010 ;
b110111 !
b110111 3
b110111 "
b110111 2
b110111 #
b110111 1
b1111 =
b101000 <
b11110 9
b1011010 8
1$
#70000
b0 0
b0 7
b0 /
b0 6
0$
b0 '
b0 *
b0 &
b0 )
b0 5
b0 %
b0 (
b0 4
#75000
b11110 +
b11110 >
b11110 ,
b11110 ?
b0 .
b0 ;
b0 -
b0 :
b1111 !
b1111 3
b101000 "
b101000 2
b101000 #
b101000 1
b11110 =
b11110 <
b0 9
b0 8
1$
#80000
b11111111 /
b11111111 6
b11111111 0
b11111111 7
0$
b11111111 '
b11111111 *
b11111111 &
b11111111 )
b11111111 5
b11111111 %
b11111111 (
b11111111 4
#85000
b0 ,
b0 ?
b0 +
b0 >
b11111111 -
b11111111 :
b11111111 .
b11111111 ;
b11110 !
b11110 3
b11110 "
b11110 2
b1011010 #
b1011010 1
b0 =
b0 <
b11111111 9
b11111111 8
1$
#90000
b10000000 0
b10000000 7
b0 /
b0 6
0$
b10000000 &
b10000000 )
b10000000 5
b0 %
b0 (
b0 4
#95000
b11111111 +
b11111111 >
b11111111 ,
b11111111 ?
b10000000 -
b10000000 :
b0 !
b0 3
b0 "
b0 2
b0 #
b0 1
b11111111 =
b11111111 <
b10000000 8
1$
#100000
b1000010 0
b1000010 7
b10110 /
b10110 6
0$
b1011000 '
b1011000 *
b10110 &
b10110 )
b10110 5
b1000010 %
b1000010 (
b1000010 4
#105000
b10000000 ,
b10000000 ?
b0 +
b0 >
b1011000 .
b1011000 ;
b1000010 -
b1000010 :
b11111111 !
b11111111 3
b11111111 "
b11111111 2
b11111111 #
b11111111 1
b0 =
b10000000 <
b1011000 9
b1000010 8
1$
#110000
b110010 0
b110010 7
b101 /
b101 6
0$
b1100100 '
b1100100 *
b110010 &
b110010 )
b110010 5
b101 %
b101 (
b101 4
#115000
b10110 +
b10110 >
b1000010 ,
b1000010 ?
b1100100 .
b1100100 ;
b110010 -
b110010 :
b0 !
b0 3
b10000000 "
b10000000 2
b10110 =
b1000010 <
b1100100 9
b110010 8
1$
#120000
b11001000 0
b11001000 7
b111 /
b111 6
0$
b1001101 '
b1001101 *
b11001000 &
b11001000 )
b11001000 5
b111 %
b111 (
b111 4
#125000
b101 +
b101 >
b110010 ,
b110010 ?
b11001000 .
b11001000 ;
b1001101 -
b1001101 :
b10110 !
b10110 3
b1000010 "
b1000010 2
b1011000 #
b1011000 1
b101 =
b110010 <
b1001101 9
b11001000 8
1$
#130000
b111100 0
b111100 7
b1111 /
b1111 6
0$
b10010110 '
b10010110 *
b1111 &
b1111 )
b1111 5
b111100 %
b111100 (
b111100 4
#135000
b111 +
b111 >
b1001101 ,
b1001101 ?
b10010110 .
b10010110 ;
b111100 -
b111100 :
b101 !
b101 3
b110010 "
b110010 2
b1100100 #
b1100100 1
b111 =
b1001101 <
b10010110 9
b111100 8
1$
#140000
b100001 /
b100001 6
b11011100 0
b11011100 7
0$
b1101111 '
b1101111 *
b100001 &
b100001 )
b100001 5
b11011100 %
b11011100 (
b11011100 4
#145000
b1111 +
b1111 >
b111100 ,
b111100 ?
b11011100 .
b11011100 ;
b1101111 -
b1101111 :
b111 !
b111 3
b1001101 "
b1001101 2
b11001000 #
b11001000 1
b1111 =
b111100 <
b1101111 9
b11011100 8
1$
#150000
b1010000 /
b1010000 6
b10111110 0
b10111110 7
0$
b1001 '
b1001 *
b10111110 &
b10111110 )
b10111110 5
b1010000 %
b1010000 (
b1010000 4
#155000
b100001 +
b100001 >
b1101111 ,
b1101111 ?
b1001 -
b1001 :
b10111110 .
b10111110 ;
b1111 !
b1111 3
b111100 "
b111100 2
b10010110 #
b10010110 1
b100001 =
b1101111 <
b1001 9
b10111110 8
1$
#160000
b11110000 0
b11110000 7
b1011111 /
b1011111 6
0$
b1 '
b1 *
b1011111 &
b1011111 )
b1011111 5
b11110000 %
b11110000 (
b11110000 4
#165000
b1010000 ,
b1010000 ?
b1001 +
b1001 >
b1 -
b1 :
b11110000 .
b11110000 ;
b100001 !
b100001 3
b1101111 "
b1101111 2
b11011100 #
b11011100 1
b1010000 =
b1001 <
b1 9
b11110000 8
1$
#170000
b101000 0
b101000 7
b101000 /
b101000 6
0$
b1010000 '
b1010000 *
b101000 &
b101000 )
b101000 5
b101000 %
b101000 (
b101000 4
#175000
b1011111 ,
b1011111 ?
b1 +
b1 >
b101000 -
b101000 :
b1010000 .
b1010000 ;
b1001 !
b1001 3
b1010000 "
b1010000 2
b10111110 #
b10111110 1
b1011111 =
b1 <
b1010000 9
b101000 8
1$
#180000
b1100011 0
b1100011 7
b100011 /
b100011 6
0$
b100011 '
b100011 *
b1100011 &
b1100011 )
b1100011 5
b100011 %
b100011 (
b100011 4
#185000
b101000 ,
b101000 ?
b101000 +
b101000 >
b1100011 .
b1100011 ;
b100011 -
b100011 :
b1 !
b1 3
b1011111 "
b1011111 2
b11110000 #
b11110000 1
b101000 =
b101000 <
b100011 9
b1100011 8
1$
#190000
b10110100 0
b10110100 7
b1000110 /
b1000110 6
0$
b1000110 '
b1000110 *
b1000110 &
b1000110 )
b1000110 5
b10110100 %
b10110100 (
b10110100 4
#195000
b100011 ,
b100011 ?
b100011 +
b100011 >
b1000110 -
b1000110 :
b10110100 .
b10110100 ;
b101000 !
b101000 3
b101000 "
b101000 2
b1010000 #
b1010000 1
b100011 =
b100011 <
b1000110 9
b10110100 8
1$
#200000
b1111101 /
b1111101 6
b1111101 0
b1111101 7
0$
b10100 '
b10100 *
b1111101 &
b1111101 )
b1111101 5
b1111101 %
b1111101 (
b1111101 4
#205000
b1000110 +
b1000110 >
b1000110 ,
b1000110 ?
b10100 -
b10100 :
b1111101 .
b1111101 ;
b100011 !
b100011 3
b100011 "
b100011 2
b1100011 #
b1100011 1
b1000110 =
b1000110 <
b10100 9
b1111101 8
1$
#210000
b110010 /
b110010 6
b10010001 0
b10010001 7
0$
b10010001 '
b10010001 *
b110010 &
b110010 )
b110010 5
b10010001 %
b10010001 (
b10010001 4
#215000
b1111101 ,
b1111101 ?
b10100 +
b10100 >
b10010001 -
b10010001 :
b10010001 .
b10010001 ;
b1000110 !
b1000110 3
b1000110 "
b1000110 2
b10110100 #
b10110100 1
b1111101 =
b10100 <
b10010001 9
b10010001 8
1$
#220000
b11001000 0
b11001000 7
b10010 /
b10010 6
0$
b11001000 '
b11001000 *
b11001000 &
b11001000 )
b11001000 5
b10010 %
b10010 (
b10010 4
#225000
b10010001 ,
b10010001 ?
b110010 +
b110010 >
b11001000 -
b11001000 :
b11001000 .
b11001000 ;
b10100 !
b10100 3
b1111101 "
b1111101 2
b1111101 #
b1111101 1
b110010 =
b10010001 <
b11001000 9
b11001000 8
1$
#230000
b1100101 0
b1100101 7
b1100100 /
b1100100 6
0$
b1100110 '
b1100110 *
b1100101 &
b1100101 )
b1100101 5
b1100100 %
b1100100 (
b1100100 4
#235000
b10010 +
b10010 >
b11001000 ,
b11001000 ?
b1100110 .
b1100110 ;
b1100101 -
b1100101 :
b110010 !
b110010 3
b10010001 "
b10010001 2
b10010001 #
b10010001 1
b10010 =
b11001000 <
b1100110 9
b1100101 8
1$
#240000
b1111111 0
b1111111 7
b10 /
b10 6
0$
b11111010 '
b11111010 *
b1111111 &
b1111111 )
b1111111 5
b10 %
b10 (
b10 4
#245000
b1100100 +
b1100100 >
b1100101 ,
b1100101 ?
b11111010 .
b11111010 ;
b1111111 -
b1111111 :
b10010 !
b10010 3
b11001000 "
b11001000 2
b11001000 #
b11001000 1
b1100100 =
b1100101 <
b11111010 9
b1111111 8
1$
#250000
b1000000 0
b1000000 7
b10000 /
b10000 6
0$
b10000000 '
b10000000 *
b10000 &
b10000 )
b10000 5
b1000000 %
b1000000 (
b1000000 4
#255000
b10 +
b10 >
b1111111 ,
b1111111 ?
b10000000 .
b10000000 ;
b1000000 -
b1000000 :
b1100100 !
b1100100 3
b1100101 "
b1100101 2
b1100110 #
b1100110 1
b10 =
b1111111 <
b10000000 9
b1000000 8
1$
#260000
b10 0
b10 7
b1 /
b1 6
0$
b11 '
b11 *
b10 &
b10 )
b10 5
b1 %
b1 (
b1 4
#265000
b10000 +
b10000 >
b1000000 ,
b1000000 ?
b11 .
b11 ;
b10 -
b10 :
b10 !
b10 3
b1111111 "
b1111111 2
b11111010 #
b11111010 1
b10000 =
b1000000 <
b11 9
b10 8
1$
#270000
b11111110 0
b11111110 7
b11111101 /
b11111101 6
0$
b11111111 '
b11111111 *
b11111110 &
b11111110 )
b11111110 5
b11111101 %
b11111101 (
b11111101 4
#275000
b10 ,
b10 ?
b1 +
b1 >
b11111111 .
b11111111 ;
b11111110 -
b11111110 :
b10000 !
b10000 3
b1000000 "
b1000000 2
b10000000 #
b10000000 1
b1 =
b10 <
b11111111 9
b11111110 8
1$
#280000
b10000111 0
b10000111 7
b1111000 /
b1111000 6
0$
b10000000 '
b10000000 *
b10000111 &
b10000111 )
b10000111 5
b1111000 %
b1111000 (
b1111000 4
#285000
b11111101 +
b11111101 >
b11111110 ,
b11111110 ?
b10000111 .
b10000111 ;
b10000000 -
b10000000 :
b1 !
b1 3
b10 "
b10 2
b11 #
b11 1
b11111101 =
b11111110 <
b10000000 9
b10000111 8
1$
#290000
b1001011 0
b1001011 7
b0 /
b0 6
0$
b10010110 '
b10010110 *
b1001011 &
b1001011 )
b1001011 5
b0 %
b0 (
b0 4
#295000
b10000000 ,
b10000000 ?
b1111000 +
b1111000 >
b10010110 .
b10010110 ;
b1001011 -
b1001011 :
b11111101 !
b11111101 3
b11111110 "
b11111110 2
b11111111 #
b11111111 1
b1111000 =
b10000000 <
b10010110 9
b1001011 8
1$
#300000
b11111111 0
b11111111 7
b1100100 /
b1100100 6
0$
b110010 '
b110010 *
b11111111 &
b11111111 )
b11111111 5
b1100100 %
b1100100 (
b1100100 4
#305000
b1001011 ,
b1001011 ?
b0 +
b0 >
b11111111 .
b11111111 ;
b110010 -
b110010 :
b1111000 !
b1111000 3
b10000000 "
b10000000 2
b10000111 #
b10000111 1
b0 =
b1001011 <
b110010 9
b11111111 8
1$
#310000
b1100001 0
b1100001 7
b110101 /
b110101 6
0$
b10010101 '
b10010101 *
b110101 &
b110101 )
b110101 5
b1100001 %
b1100001 (
b1100001 4
#315000
b110010 +
b110010 >
b1100100 ,
b1100100 ?
b1100001 -
b1100001 :
b10010101 .
b10010101 ;
b0 !
b0 3
b1001011 "
b1001011 2
b10010110 #
b10010110 1
b1100100 =
b110010 <
b10010101 9
b1100001 8
1$
#320000
b1011001 /
b1011001 6
b10010000 0
b10010000 7
0$
b110111 '
b110111 *
b10010000 &
b10010000 )
b10010000 5
b1011001 %
b1011001 (
b1011001 4
#325000
b1100001 ,
b1100001 ?
b110101 +
b110101 >
b10010000 .
b10010000 ;
b110111 -
b110111 :
b110010 !
b110010 3
b1100100 "
b1100100 2
b11111111 #
b11111111 1
b110101 =
b1100001 <
b110111 9
b10010000 8
1$
#330000
b1011010 0
b1011010 7
b11110 /
b11110 6
0$
b111100 '
b111100 *
b11110 &
b11110 )
b11110 5
b1011010 %
b1011010 (
b1011010 4
#335000
b110111 +
b110111 >
b1011001 ,
b1011001 ?
b111100 -
b111100 :
b1011010 .
b1011010 ;
b110101 !
b110101 3
b1100001 "
b1100001 2
b10010101 #
b10010101 1
b1011001 =
b110111 <
b111100 9
b1011010 8
1$
#340000
b11101 /
b11101 6
b1001001 0
b1001001 7
0$
b10101011 '
b10101011 *
b11101 &
b11101 )
b11101 5
b1001001 %
b1001001 (
b1001001 4
#345000
b111100 ,
b111100 ?
b11110 +
b11110 >
b1001001 -
b1001001 :
b10101011 .
b10101011 ;
b110111 !
b110111 3
b1011001 "
b1011001 2
b10010000 #
b10010000 1
b11110 =
b111100 <
b10101011 9
b1001001 8
1$
#350000
b1010100 /
b1010100 6
b10100110 0
b10100110 7
0$
b101010 '
b101010 *
b10100110 &
b10100110 )
b10100110 5
b1010100 %
b1010100 (
b1010100 4
#355000
b11101 +
b11101 >
b1001001 ,
b1001001 ?
b10100110 .
b10100110 ;
b101010 -
b101010 :
b11110 !
b11110 3
b111100 "
b111100 2
b1011010 #
b1011010 1
b11101 =
b1001001 <
b101010 9
b10100110 8
1$
#360000
0$
#365000
b101010 +
b101010 >
b1010100 ,
b1010100 ?
b11101 !
b11101 3
b1001001 "
b1001001 2
b10101011 #
b10101011 1
b1010100 =
b101010 <
1$
#370000
0$
#375000
b101010 !
b101010 3
b1010100 "
b1010100 2
b10100110 #
b10100110 1
1$
