Comparator_8bits.v
module Comparator_8bits(Max, Min, A, B/*, clk*/);
    //input             clk;
    input       [7:0] A, B;
    output      [7:0] Max, Min;

    // always @(posedge clk) begin
    //     Max <= (A > B) ? A : B;
    //     Min <= (A < B) ? A : B;
    // end

    assign Max = (A > B) ? A : B;
    assign Min = (A < B) ? A : B;
endmodule

Ascending_Sorter_3inputs_8bits.v
//`include "Comparator_8bits.v"

module Ascending_Sorter_3inputs_8bits(min, mid, max, 
                                      in0, in1, in2,
                                      clk);
    
    input   wire        clk;
    input   wire [7:0]  in0, in1, in2;
    output  reg  [7:0]  min, mid, max;

    reg [7:0] rin0, rin1, rin2;
    reg       cmp0, cmp1, cmp2;  //0: in0 < in1?; 1:in1 < in2?; in0 < in2? 

    always @(posedge clk) begin
        //STAGE 0
        rin0 <= in0;
        rin1 <= in1;
        rin2 <= in2;
        
        cmp0 <= (in0 < in1);
        cmp1 <= (in1 < in2);
        cmp2 <= (in2 < in0);

        // STAGE 1
        case ({cmp0, cmp1, cmp2})
            //in0 < in1 < in2
            3'b110: begin min <= rin0; mid <= rin1; max <= rin2; end 

            //in0 < in2 < in1
            3'b100: begin min <= rin0; mid <= rin2; max <= rin1; end 

            //in1 < in0 < in2
            3'b010: begin min <= rin1; mid <= rin0; max <= rin2; end 

            //in1 < in2 < in0
            3'b011: begin min <= rin1; mid <= rin2; max <= rin0; end 

            //in2 < in0 < in1
            3'b101: begin min <= rin2; mid <= rin0; max <= rin1; end 

            //in2 < in1 < in0
            3'b001: begin min <= rin2; mid <= rin1; max <= rin0; end 

            default: begin min <= rin0; mid <= rin1; max <= rin2; end
        endcase
    end 

endmodule

Median_Finder_9inputs_8bits.v
//`include "Ascending_Sorter_3inputs_8bits.v"

module Median_Finder_9inputs_8bits(
    output wire [7:0] median_pixel,
    input  wire [7:0] pixel0, pixel1, pixel2,
    input  wire [7:0] pixel3, pixel4, pixel5,
    input  wire [7:0] pixel6, pixel7, pixel8,
    input  wire       clk
);

    // reg     [7:0] rmin0, rmid0, rmax0;
    // reg     [7:0] rmin1, rmid1, rmax1;
    // reg     [7:0] rmin2, rmid2, rmax2;
    
    wire    [7:0] wmin0, wmid0, wmax0;
    wire    [7:0] wmin1, wmid1, wmax1;
    wire    [7:0] wmin2, wmid2, wmax2;

    //reg     [7:0] rmax_col0, rmid_col1, rmin_col2;
    wire    [7:0] wmax_col0, wmid_col1, wmin_col2;

    //STAGE 0
    Ascending_Sorter_3inputs_8bits Row0(
        .min(wmin0), .mid(wmid0), .max(wmax0),
        .in0(pixel0), .in1(pixel1), .in2(pixel2),
        .clk(clk)
    );

    Ascending_Sorter_3inputs_8bits Row1(
        .min(wmin1), .mid(wmid1), .max(wmax1),
        .in0(pixel3), .in1(pixel4), .in2(pixel5),
        .clk(clk)
    );

    Ascending_Sorter_3inputs_8bits Row2(
        .min(wmin2), .mid(wmid2), .max(wmax2),
        .in0(pixel6), .in1(pixel7), .in2(pixel8),
        .clk(clk)
    );


    //STAGE 1
    Ascending_Sorter_3inputs_8bits FindMax(
        .max(wmax_col0),
        .in0(wmin0), .in1(wmin1), .in2(wmin2),        
        .clk(clk)
    );

    Ascending_Sorter_3inputs_8bits FindMid(
        .mid(wmid_col1),
        .in0(wmid0), .in1(wmid1), .in2(wmid2),        
        .clk(clk)
    );

    Ascending_Sorter_3inputs_8bits FindMin(
        .min(wmin_col2),
        .in0(wmax0), .in1(wmax1), .in2(wmax2),        
        .clk(clk)
    );

    // always @(posedge clk) begin
    //     rmin0 <= wmin0;
    //     rmid0 <= wmid0;
    //     rmax0 <= wmax0;

    //     rmin1 <= wmin1;
    //     rmid1 <= wmid1;
    //     rmax1 <= wmax1;

    //     rmin2 <= wmin2;
    //     rmid2 <= wmid2;
    //     rmax2 <= wmax2;

    //     rmax_col0 <= wmax_col0;
    //     rmid_col1 <= wmid_col1;
    //     rmin_col2 <= wmin_col2;
    // end

    
    
    // assign max_col0 = (rmin0 > rmin1) ? ((rmin0 > rmin2) ? rmin0 : rmin2) : ((rmin1 > rmin2) ? rmin1 : rmin2);

    // assign mid_col1 = (rmid0 > rmid1) ? 
    //              ((rmid1 > rmid2) ? rmid1 : ((rmid0 > rmid2) ? rmid2 : rmid0)) : 
    //              ((rmid0 > rmid2) ? rmid0 : ((rmid1 > rmid2) ? rmid2 : rmid1));
        
    // assign min_col2 = (rmax0 < rmax1) ? ((rmax0 < rmax2) ? rmax0 : rmax2) : ((rmax1 < rmax2) ? rmax1 : rmax2);


    Ascending_Sorter_3inputs_8bits FindMedian(
        .mid(median_pixel),
        .in0(wmax_col0), .in1(wmid_col1), .in2(wmin_col2),
        .clk(clk)
    );

endmodule

tb_Median_Finder_9inputs_8bits.v
`timescale 10ns / 1ps
`include "Median_Finder_9inputs_8bits.v"

module tb_Median_Finder_9inputs_8bits;
    reg     [7:0] pixel0, pixel1, pixel2;
    reg     [7:0] pixel3, pixel4, pixel5;
    reg     [7:0] pixel6, pixel7, pixel8;
    reg           clk;
    wire    [7:0] median_pixel;

    Median_Finder_9inputs_8bits utt(
        .median_pixel(median_pixel),
        .pixel0(pixel0), .pixel1(pixel1), .pixel2(pixel2), 
        .pixel3(pixel3), .pixel4(pixel4), .pixel5(pixel5), 
        .pixel6(pixel6), .pixel7(pixel7), .pixel8(pixel8),
        .clk(clk)
    );

    initial begin
        clk = 0;
    end

    always #5 clk = ~clk;

    initial begin
        $dumpfile("tb_Median_Finder_9inputs_8bits.vcd");
        $dumpvars(0, tb_Median_Finder_9inputs_8bits);

        pixel0 = 8'd1; pixel1 = 8'd2; pixel2 = 8'd3;
        pixel3 = 8'd1; pixel4 = 8'd2; pixel5 = 8'd3;
        pixel6 = 8'd1; pixel7 = 8'd2; pixel8 = 8'd3;

        #10
        pixel0 = 8'd1; pixel1 = 8'd1; pixel2 = 8'd1;
        pixel3 = 8'd1; pixel4 = 8'd1; pixel5 = 8'd1;
        pixel6 = 8'd1; pixel7 = 8'd1; pixel8 = 8'd1;

        #10
        pixel0 = 8'd1; pixel1 = 8'd2; pixel2 = 8'd3;
        pixel3 = 8'd4; pixel4 = 8'd5; pixel5 = 8'd6;
        pixel6 = 8'd7; pixel7 = 8'd8; pixel8 = 8'd9;

        #10
        pixel0 = 8'd2; pixel1 = 8'd12; pixel2 = 8'd36;
        pixel3 = 8'd5; pixel4 = 8'd27; pixel5 = 8'd18;
        pixel6 = 8'd8; pixel7 = 8'd25; pixel8 = 8'd22;

        #10
        pixel0 = 8'd18; pixel1 = 8'd20; pixel2 = 8'd3;
        pixel3 = 8'd12; pixel4 = 8'd12; pixel5 = 8'd6;
        pixel6 = 8'd15; pixel7 = 8'd12; pixel8 = 8'd9;

        #10
        pixel0 = 8'd50; pixel1 = 8'd100; pixel2 = 8'd150;
        pixel3 = 8'd40; pixel4 = 8'd90; pixel5 = 8'd140;
        pixel6 = 8'd30; pixel7 = 8'd80; pixel8 = 8'd130;

        #10
        pixel0 = 8'd255; pixel1 = 8'd200; pixel2 = 8'd180;
        pixel3 = 8'd170; pixel4 = 8'd160; pixel5 = 8'd150;
        pixel6 = 8'd100; pixel7 = 8'd50; pixel8 = 8'd0;

        #10
        pixel0 = 8'd64; pixel1 = 8'd32; pixel2 = 8'd16;
        pixel3 = 8'd128; pixel4 = 8'd64; pixel5 = 8'd32;
        pixel6 = 8'd8; pixel7 = 8'd4; pixel8 = 8'd2;

        #10
        pixel0 = 8'd111; pixel1 = 8'd111; pixel2 = 8'd222;
        pixel3 = 8'd222; pixel4 = 8'd111; pixel5 = 8'd222;
        pixel6 = 8'd111; pixel7 = 8'd222; pixel8 = 8'd111;

        #10
        pixel0 = 8'd5; pixel1 = 8'd95; pixel2 = 8'd45;
        pixel3 = 8'd75; pixel4 = 8'd25; pixel5 = 8'd85;
        pixel6 = 8'd55; pixel7 = 8'd65; pixel8 = 8'd35;

        #10
        pixel0 = 8'd128; pixel1 = 8'd128; pixel2 = 8'd128;
        pixel3 = 8'd128; pixel4 = 8'd255; pixel5 = 8'd128;
        pixel6 = 8'd128; pixel7 = 8'd128; pixel8 = 8'd128;

        #10
        pixel0 = 8'd200; pixel1 = 8'd200; pixel2 = 8'd200;
        pixel3 = 8'd200; pixel4 = 8'd0;   pixel5 = 8'd200;
        pixel6 = 8'd200; pixel7 = 8'd200; pixel8 = 8'd200;

        #10
        pixel0 = 8'd10;  pixel1 = 8'd10;  pixel2 = 8'd200;
        pixel3 = 8'd10;  pixel4 = 8'd10;  pixel5 = 8'd200;
        pixel6 = 8'd10;  pixel7 = 8'd10;  pixel8 = 8'd200;

        #10
        pixel0 = 8'd200; pixel1 = 8'd200; pixel2 = 8'd200;
        pixel3 = 8'd200; pixel4 = 8'd200; pixel5 = 8'd200;
        pixel6 = 8'd50;  pixel7 = 8'd50;  pixel8 = 8'd50;

        #10
        pixel0 = 8'd0;   pixel1 = 8'd255; pixel2 = 8'd0;
        pixel3 = 8'd255; pixel4 = 8'd0;   pixel5 = 8'd255;
        pixel6 = 8'd0;   pixel7 = 8'd255; pixel8 = 8'd0;

        #10
        pixel0 = 8'd90; pixel1 = 8'd80; pixel2 = 8'd70;
        pixel3 = 8'd60; pixel4 = 8'd50; pixel5 = 8'd40;
        pixel6 = 8'd30; pixel7 = 8'd20; pixel8 = 8'd10;

        #10
        pixel0 = 8'd200; pixel1 = 8'd5;   pixel2 = 8'd100;
        pixel3 = 8'd5;   pixel4 = 8'd200; pixel5 = 8'd100;
        pixel6 = 8'd100; pixel7 = 8'd200; pixel8 = 8'd5;

        #10
        pixel0 = 8'd0;   pixel1 = 8'd255; pixel2 = 8'd0;
        pixel3 = 8'd255; pixel4 = 8'd254; pixel5 = 8'd0;
        pixel6 = 8'd255; pixel7 = 8'd0;   pixel8 = 8'd255;

        #150;
        $finish;
    end

endmodule

tb_Median_Finder_9inputs_8bits.vcd
$date
	Thu Dec 25 14:04:05 2025
$end
$version
	Icarus Verilog
$end
$timescale
	1ps
$end
$scope module tb_Median_Finder_9inputs_8bits $end
$var wire 8 ! median_pixel [7:0] $end
$var reg 1 " clk $end
$var reg 8 # pixel0 [7:0] $end
$var reg 8 $ pixel1 [7:0] $end
$var reg 8 % pixel2 [7:0] $end
$var reg 8 & pixel3 [7:0] $end
$var reg 8 ' pixel4 [7:0] $end
$var reg 8 ( pixel5 [7:0] $end
$var reg 8 ) pixel6 [7:0] $end
$var reg 8 * pixel7 [7:0] $end
$var reg 8 + pixel8 [7:0] $end
$scope module utt $end
$var wire 1 " clk $end
$var wire 8 , pixel0 [7:0] $end
$var wire 8 - pixel1 [7:0] $end
$var wire 8 . pixel2 [7:0] $end
$var wire 8 / pixel3 [7:0] $end
$var wire 8 0 pixel4 [7:0] $end
$var wire 8 1 pixel5 [7:0] $end
$var wire 8 2 pixel6 [7:0] $end
$var wire 8 3 pixel7 [7:0] $end
$var wire 8 4 pixel8 [7:0] $end
$var wire 8 5 wmin_col2 [7:0] $end
$var wire 8 6 wmin2 [7:0] $end
$var wire 8 7 wmin1 [7:0] $end
$var wire 8 8 wmin0 [7:0] $end
$var wire 8 9 wmid_col1 [7:0] $end
$var wire 8 : wmid2 [7:0] $end
$var wire 8 ; wmid1 [7:0] $end
$var wire 8 < wmid0 [7:0] $end
$var wire 8 = wmax_col0 [7:0] $end
$var wire 8 > wmax2 [7:0] $end
$var wire 8 ? wmax1 [7:0] $end
$var wire 8 @ wmax0 [7:0] $end
$var wire 8 A median_pixel [7:0] $end
$scope module FindMax $end
$var wire 1 " clk $end
$var wire 8 B in2 [7:0] $end
$var wire 8 C in1 [7:0] $end
$var wire 8 D in0 [7:0] $end
$var reg 1 E cmp0 $end
$var reg 1 F cmp1 $end
$var reg 1 G cmp2 $end
$var reg 8 H max [7:0] $end
$var reg 8 I mid [7:0] $end
$var reg 8 J min [7:0] $end
$var reg 8 K rin0 [7:0] $end
$var reg 8 L rin1 [7:0] $end
$var reg 8 M rin2 [7:0] $end
$upscope $end
$scope module FindMedian $end
$var wire 1 " clk $end
$var wire 8 N in0 [7:0] $end
$var wire 8 O in2 [7:0] $end
$var wire 8 P in1 [7:0] $end
$var reg 1 Q cmp0 $end
$var reg 1 R cmp1 $end
$var reg 1 S cmp2 $end
$var reg 8 T max [7:0] $end
$var reg 8 U mid [7:0] $end
$var reg 8 V min [7:0] $end
$var reg 8 W rin0 [7:0] $end
$var reg 8 X rin1 [7:0] $end
$var reg 8 Y rin2 [7:0] $end
$upscope $end
$scope module FindMid $end
$var wire 1 " clk $end
$var wire 8 Z in2 [7:0] $end
$var wire 8 [ in1 [7:0] $end
$var wire 8 \ in0 [7:0] $end
$var reg 1 ] cmp0 $end
$var reg 1 ^ cmp1 $end
$var reg 1 _ cmp2 $end
$var reg 8 ` max [7:0] $end
$var reg 8 a mid [7:0] $end
$var reg 8 b min [7:0] $end
$var reg 8 c rin0 [7:0] $end
$var reg 8 d rin1 [7:0] $end
$var reg 8 e rin2 [7:0] $end
$upscope $end
$scope module FindMin $end
$var wire 1 " clk $end
$var wire 8 f in2 [7:0] $end
$var wire 8 g in1 [7:0] $end
$var wire 8 h in0 [7:0] $end
$var reg 1 i cmp0 $end
$var reg 1 j cmp1 $end
$var reg 1 k cmp2 $end
$var reg 8 l max [7:0] $end
$var reg 8 m mid [7:0] $end
$var reg 8 n min [7:0] $end
$var reg 8 o rin0 [7:0] $end
$var reg 8 p rin1 [7:0] $end
$var reg 8 q rin2 [7:0] $end
$upscope $end
$scope module Row0 $end
$var wire 1 " clk $end
$var wire 8 r in0 [7:0] $end
$var wire 8 s in1 [7:0] $end
$var wire 8 t in2 [7:0] $end
$var reg 1 u cmp0 $end
$var reg 1 v cmp1 $end
$var reg 1 w cmp2 $end
$var reg 8 x max [7:0] $end
$var reg 8 y mid [7:0] $end
$var reg 8 z min [7:0] $end
$var reg 8 { rin0 [7:0] $end
$var reg 8 | rin1 [7:0] $end
$var reg 8 } rin2 [7:0] $end
$upscope $end
$scope module Row1 $end
$var wire 1 " clk $end
$var wire 8 ~ in0 [7:0] $end
$var wire 8 !" in1 [7:0] $end
$var wire 8 "" in2 [7:0] $end
$var reg 1 #" cmp0 $end
$var reg 1 $" cmp1 $end
$var reg 1 %" cmp2 $end
$var reg 8 &" max [7:0] $end
$var reg 8 '" mid [7:0] $end
$var reg 8 (" min [7:0] $end
$var reg 8 )" rin0 [7:0] $end
$var reg 8 *" rin1 [7:0] $end
$var reg 8 +" rin2 [7:0] $end
$upscope $end
$scope module Row2 $end
$var wire 1 " clk $end
$var wire 8 ," in0 [7:0] $end
$var wire 8 -" in1 [7:0] $end
$var wire 8 ." in2 [7:0] $end
$var reg 1 /" cmp0 $end
$var reg 1 0" cmp1 $end
$var reg 1 1" cmp2 $end
$var reg 8 2" max [7:0] $end
$var reg 8 3" mid [7:0] $end
$var reg 8 4" min [7:0] $end
$var reg 8 5" rin0 [7:0] $end
$var reg 8 6" rin1 [7:0] $end
$var reg 8 7" rin2 [7:0] $end
$upscope $end
$upscope $end
$upscope $end
$enddefinitions $end
$comment Show the parameter values. $end
$dumpall
$end
#0
$dumpvars
bx 7"
bx 6"
bx 5"
bx 4"
bx 3"
bx 2"
x1"
x0"
x/"
b11 ."
b10 -"
b1 ,"
bx +"
bx *"
bx )"
bx ("
bx '"
bx &"
x%"
x$"
x#"
b11 ""
b10 !"
b1 ~
bx }
bx |
bx {
bx z
bx y
bx x
xw
xv
xu
b11 t
b10 s
b1 r
bx q
bx p
bx o
bx n
bx m
bx l
xk
xj
xi
bx h
bx g
bx f
bx e
bx d
bx c
bx b
bx a
bx `
x_
x^
x]
bx \
bx [
bx Z
bx Y
bx X
bx W
bx V
bx U
bx T
xS
xR
xQ
bx P
bx O
bx N
bx M
bx L
bx K
bx J
bx I
bx H
xG
xF
xE
bx D
bx C
bx B
bx A
bx @
bx ?
bx >
bx =
bx <
bx ;
bx :
bx 9
bx 8
bx 7
bx 6
bx 5
b11 4
b10 3
b1 2
b11 1
b10 0
b1 /
b11 .
b10 -
b1 ,
b11 +
b10 *
b1 )
b11 (
b10 '
b1 &
b11 %
b10 $
b1 #
0"
bx !
$end
#50000
0w
1v
1u
b11 }
b10 |
b1 {
0%"
1$"
1#"
b11 +"
b10 *"
b1 )"
01"
10"
1/"
b11 7"
b10 6"
b1 5"
1"
#100000
0"
b1 +
b1 4
b1 ."
b1 *
b1 3
b1 -"
b1 (
b1 1
b1 ""
b1 '
b1 0
b1 !"
b1 %
b1 .
b1 t
b1 $
b1 -
b1 s
#150000
b11 >
b11 f
b11 2"
b10 :
b10 Z
b10 3"
b1 6
b1 B
b1 4"
00"
0/"
b1 7"
b1 6"
b11 ?
b11 g
b11 &"
b10 ;
b10 [
b10 '"
b1 7
b1 C
b1 ("
0$"
0#"
b1 +"
b1 *"
b11 @
b11 h
b11 x
b10 <
b10 \
b10 y
b1 8
b1 D
b1 z
0v
0u
b1 }
b1 |
1"
#200000
0"
b1001 +
b1001 4
b1001 ."
b1000 *
b1000 3
b1000 -"
b111 )
b111 2
b111 ,"
b110 (
b110 1
b110 ""
b101 '
b101 0
b101 !"
b100 &
b100 /
b100 ~
b11 %
b11 .
b11 t
b10 $
b10 -
b10 s
#250000
b1 @
b1 h
b1 x
b1 <
b1 \
b1 y
1v
1u
b11 }
b10 |
b1 ?
b1 g
b1 &"
b1 ;
b1 [
b1 '"
1$"
1#"
b110 +"
b101 *"
b100 )"
b1 >
b1 f
b1 2"
b1 :
b1 Z
b1 3"
10"
1/"
b1001 7"
b1000 6"
b111 5"
0G
0F
0E
b1 M
b1 L
b1 K
0_
0^
0]
b10 e
b10 d
b10 c
0k
0j
0i
b11 q
b11 p
b11 o
1"
#300000
0"
b10110 +
b10110 4
b10110 ."
b11001 *
b11001 3
b11001 -"
b1000 )
b1000 2
b1000 ,"
b10010 (
b10010 1
b10010 ""
b11011 '
b11011 0
b11011 !"
b101 &
b101 /
b101 ~
b100100 %
b100100 .
b100100 t
b1100 $
b1100 -
b1100 s
b10 #
b10 ,
b10 r
#350000
b11 l
b11 m
b11 5
b11 O
b11 n
b1 q
b1 p
b1 o
b10 `
b10 9
b10 P
b10 a
b10 b
b1 e
b1 d
b1 c
b1 =
b1 H
b1 N
b1 I
b1 J
b1001 >
b1001 f
b1001 2"
b1000 :
b1000 Z
b1000 3"
b111 6
b111 B
b111 4"
00"
b10110 7"
b11001 6"
b1000 5"
b110 ?
b110 g
b110 &"
b101 ;
b101 [
b101 '"
b100 7
b100 C
b100 ("
0$"
b10010 +"
b11011 *"
b101 )"
b11 @
b11 h
b11 x
b10 <
b10 \
b10 y
b100100 }
b1100 |
b10 {
1"
#400000
0"
b1001 +
b1001 4
b1001 ."
b1100 *
b1100 3
b1100 -"
b1111 )
b1111 2
b1111 ,"
b110 (
b110 1
b110 ""
b1100 '
b1100 0
b1100 !"
b1100 &
b1100 /
b1100 ~
b11 %
b11 .
b11 t
b10100 $
b10100 -
b10100 s
b10010 #
b10010 ,
b10010 r
#450000
b100100 @
b100100 h
b100100 x
b1100 <
b1100 \
b1100 y
b10 8
b10 D
b10 z
1w
0v
b11 }
b10100 |
b10010 {
b11011 ?
b11011 g
b11011 &"
b10010 ;
b10010 [
b10010 '"
b101 7
b101 C
b101 ("
1%"
0#"
b110 +"
b1100 *"
b1100 )"
b11001 >
b11001 f
b11001 2"
b10110 :
b10110 Z
b10110 3"
b1000 6
b1000 B
b1000 4"
11"
0/"
b1001 7"
b1100 6"
b1111 5"
1F
1E
b111 M
b100 L
b1 `
b1 9
b1 P
b1 a
b1 b
1^
1]
b1000 e
b101 d
b10 c
b1 l
b1 m
b1 5
b1 O
b1 n
1j
1i
b1001 q
b110 p
b11 o
0S
1R
1Q
b11 Y
b10 X
b1 W
1"
#500000
0"
b10000010 +
b10000010 4
b10000010 ."
b1010000 *
b1010000 3
b1010000 -"
b11110 )
b11110 2
b11110 ,"
b10001100 (
b10001100 1
b10001100 ""
b1011010 '
b1011010 0
b1011010 !"
b101000 &
b101000 /
b101000 ~
b10010110 %
b10010110 .
b10010110 t
b1100100 $
b1100100 -
b1100100 s
b110010 #
b110010 ,
b110010 r
#550000
b11 T
b10 !
b10 A
b10 U
b1 V
0R
0Q
b1 Y
b1 X
b1001 l
b110 m
b11 5
b11 O
b11 n
1k
0j
0i
b11001 q
b11011 p
b100100 o
b1000 `
b101 9
b101 P
b101 a
b10 b
b10110 e
b10010 d
b1100 c
b111 =
b111 H
b111 N
b100 I
b1000 M
b101 L
b10 K
b1111 >
b1111 f
b1111 2"
b1100 :
b1100 Z
b1100 3"
b1001 6
b1001 B
b1001 4"
01"
10"
1/"
b10000010 7"
b1010000 6"
b11110 5"
b1100 ?
b1100 g
b1100 &"
b1100 ;
b1100 [
b1100 '"
b110 7
b110 C
b110 ("
0%"
1$"
1#"
b10001100 +"
b1011010 *"
b101000 )"
b10100 @
b10100 h
b10100 x
b10010 <
b10010 \
b10010 y
b11 8
b11 D
b11 z
0w
1v
b10010110 }
b1100100 |
b110010 {
1"
#600000
0"
b0 +
b0 4
b0 ."
b110010 *
b110010 3
b110010 -"
b1100100 )
b1100100 2
b1100100 ,"
b10010110 (
b10010110 1
b10010110 ""
b10100000 '
b10100000 0
b10100000 !"
b10101010 &
b10101010 /
b10101010 ~
b10110100 %
b10110100 .
b10110100 t
b11001000 $
b11001000 -
b11001000 s
b11111111 #
b11111111 ,
b11111111 r
#650000
b10010110 @
b10010110 h
b10010110 x
b1100100 <
b1100100 \
b1100100 y
b110010 8
b110010 D
b110010 z
1w
0v
0u
b10110100 }
b11001000 |
b11111111 {
b10001100 ?
b10001100 g
b10001100 &"
b1011010 ;
b1011010 [
b1011010 '"
b101000 7
b101000 C
b101000 ("
1%"
0$"
0#"
b10010110 +"
b10100000 *"
b10101010 )"
b10000010 >
b10000010 f
b10000010 2"
b1010000 :
b1010000 Z
b1010000 3"
b11110 6
b11110 B
b11110 4"
11"
00"
0/"
b0 7"
b110010 6"
b1100100 5"
b1000 =
b1000 H
b1000 N
b101 I
b10 J
b1001 M
b110 L
b11 K
b10110 `
b10010 9
b10010 P
b10010 a
b1100 b
1_
0^
0]
b1100 e
b1100 d
b10010 c
b100100 l
b11011 m
b11001 5
b11001 O
b11001 n
1j
b1111 q
b1100 p
b10100 o
b1 T
b1 !
b1 A
b1 U
1S
b11 Y
b101 X
b111 W
1"
#700000
0"
b10 +
b10 4
b10 ."
b100 *
b100 3
b100 -"
b1000 )
b1000 2
b1000 ,"
b100000 (
b100000 1
b100000 ""
b1000000 '
b1000000 0
b1000000 !"
b10000000 &
b10000000 /
b10000000 ~
b10000 %
b10000 .
b10000 t
b100000 $
b100000 -
b100000 s
b1000000 #
b1000000 ,
b1000000 r
#750000
b111 T
b101 !
b101 A
b101 U
b11 V
0S
1R
1Q
b11001 Y
b10010 X
b1000 W
b10100 l
b1111 m
b1100 5
b1100 O
b1100 n
0j
b10000010 q
b10001100 p
b10010110 o
b10010 `
b1100 9
b1100 P
b1100 a
b1010000 e
b1011010 d
b1100100 c
b1001 =
b1001 H
b1001 N
b110 I
b11 J
1G
0F
0E
b11110 M
b101000 L
b110010 K
b1100100 >
b1100100 f
b1100100 2"
b110010 :
b110010 Z
b110010 3"
b0 6
b0 B
b0 4"
b10 7"
b100 6"
b1000 5"
b10101010 ?
b10101010 g
b10101010 &"
b10100000 ;
b10100000 [
b10100000 '"
b10010110 7
b10010110 C
b10010110 ("
b100000 +"
b1000000 *"
b10000000 )"
b11111111 @
b11111111 h
b11111111 x
b11001000 <
b11001000 \
b11001000 y
b10110100 8
b10110100 D
b10110100 z
b10000 }
b100000 |
b1000000 {
1"
#800000
0"
b1101111 +
b1101111 4
b1101111 ."
b11011110 *
b11011110 3
b11011110 -"
b1101111 )
b1101111 2
b1101111 ,"
b11011110 (
b11011110 1
b11011110 ""
b1101111 '
b1101111 0
b1101111 !"
b11011110 &
b11011110 /
b11011110 ~
b11011110 %
b11011110 .
b11011110 t
b1101111 $
b1101111 -
b1101111 s
b1101111 #
b1101111 ,
b1101111 r
#850000
b1000000 @
b1000000 h
b1000000 x
b100000 <
b100000 \
b100000 y
b10000 8
b10000 D
b10000 z
0w
1v
b11011110 }
b1101111 |
b1101111 {
b10000000 ?
b10000000 g
b10000000 &"
b1000000 ;
b1000000 [
b1000000 '"
b100000 7
b100000 C
b100000 ("
0%"
1$"
b11011110 +"
b1101111 *"
b11011110 )"
b1000 >
b1000 f
b1000 2"
b100 :
b100 Z
b100 3"
b10 6
b10 B
b10 4"
01"
1/"
b1101111 7"
b11011110 6"
b1101111 5"
b110010 =
b110010 H
b110010 N
b101000 I
b11110 J
b0 M
b10010110 L
b10110100 K
b1100100 `
b1011010 9
b1011010 P
b1011010 a
b1010000 b
b110010 e
b10100000 d
b11001000 c
b10010110 l
b10001100 m
b10000010 5
b10000010 O
b10000010 n
b1100100 q
b10101010 p
b11111111 o
b11001 T
b10010 !
b10010 A
b10010 U
b1000 V
0R
b1100 Y
b1100 X
b1001 W
1"
#900000
0"
b100011 +
b100011 4
b100011 ."
b1000001 *
b1000001 3
b1000001 -"
b110111 )
b110111 2
b110111 ,"
b1010101 (
b1010101 1
b1010101 ""
b11001 '
b11001 0
b11001 !"
b1001011 &
b1001011 /
b1001011 ~
b101101 %
b101101 .
b101101 t
b1011111 $
b1011111 -
b1011111 s
b101 #
b101 ,
b101 r
#950000
b1100 T
b1100 !
b1100 A
b1100 U
b1001 V
1R
b10000010 Y
b1011010 X
b110010 W
b11111111 l
b10101010 m
b1100100 5
b1100100 O
b1100100 n
1i
b1000 q
b10000000 p
b1000000 o
b11001000 `
b10100000 9
b10100000 P
b10100000 a
b110010 b
1]
b100 e
b1000000 d
b100000 c
b10110100 =
b10110100 H
b10110100 N
b10010110 I
b0 J
1E
b10 M
b100000 L
b10000 K
b11011110 >
b11011110 f
b11011110 2"
b1101111 :
b1101111 Z
b1101111 3"
b1101111 6
b1101111 B
b1101111 4"
11"
b100011 7"
b1000001 6"
b110111 5"
b11011110 ?
b11011110 g
b11011110 &"
b11011110 ;
b11011110 [
b11011110 '"
b1101111 7
b1101111 C
b1101111 ("
b1010101 +"
b11001 *"
b1001011 )"
b11011110 @
b11011110 h
b11011110 x
b1101111 <
b1101111 \
b1101111 y
b1101111 8
b1101111 D
b1101111 z
0v
1u
b101101 }
b1011111 |
b101 {
1"
#1000000
0"
b10000000 +
b10000000 4
b10000000 ."
b10000000 *
b10000000 3
b10000000 -"
b10000000 )
b10000000 2
b10000000 ,"
b10000000 (
b10000000 1
b10000000 ""
b11111111 '
b11111111 0
b11111111 !"
b10000000 &
b10000000 /
b10000000 ~
b10000000 %
b10000000 .
b10000000 t
b10000000 $
b10000000 -
b10000000 s
b10000000 #
b10000000 ,
b10000000 r
#1050000
b1011111 @
b1011111 h
b1011111 x
b101101 <
b101101 \
b101101 y
b101 8
b101 D
b101 z
0u
b10000000 }
b10000000 |
b10000000 {
b1010101 ?
b1010101 g
b1010101 &"
b1001011 ;
b1001011 [
b1001011 '"
b11001 7
b11001 C
b11001 ("
0$"
1#"
b10000000 +"
b11111111 *"
b10000000 )"
b1000001 >
b1000001 f
b1000001 2"
b110111 :
b110111 Z
b110111 3"
b100011 6
b100011 B
b100011 4"
01"
0/"
b10000000 7"
b10000000 6"
b10000000 5"
b100000 =
b100000 H
b100000 N
b10000 I
b10 J
0G
0E
b1101111 M
b1101111 L
b1101111 K
b1000000 `
b100000 9
b100000 P
b100000 a
b100 b
0_
b1101111 e
b11011110 d
b1101111 c
b10000000 l
b1000000 m
b1000 5
b1000 O
b1000 n
0k
0i
b11011110 q
b11011110 p
b11011110 o
b10000010 T
b1011010 !
b1011010 A
b1011010 U
b110010 V
1S
0R
0Q
b1100100 Y
b10100000 X
b10110100 W
1"
#1100000
0"
b11001000 +
b11001000 4
b11001000 ."
b11001000 *
b11001000 3
b11001000 -"
b11001000 )
b11001000 2
b11001000 ,"
b11001000 (
b11001000 1
b11001000 ""
b0 '
b0 0
b0 !"
b11001000 &
b11001000 /
b11001000 ~
b11001000 %
b11001000 .
b11001000 t
b11001000 $
b11001000 -
b11001000 s
b11001000 #
b11001000 ,
b11001000 r
#1150000
b10110100 T
b10100000 !
b10100000 A
b10100000 U
b1100100 V
b1000 Y
b100000 X
b100000 W
b11011110 l
b11011110 m
b11011110 5
b11011110 O
b11011110 n
1k
b1000001 q
b1010101 p
b1011111 o
b11011110 `
b1101111 9
b1101111 P
b1101111 a
b1101111 b
b110111 e
b1001011 d
b101101 c
b1101111 =
b1101111 H
b1101111 N
b1101111 I
b1101111 J
1F
1E
b100011 M
b11001 L
b101 K
b10000000 >
b10000000 f
b10000000 2"
b10000000 :
b10000000 Z
b10000000 3"
b10000000 6
b10000000 B
b10000000 4"
b11001000 7"
b11001000 6"
b11001000 5"
b11111111 ?
b11111111 g
b11111111 &"
b10000000 ;
b10000000 [
b10000000 '"
b10000000 7
b10000000 C
b10000000 ("
1$"
0#"
b11001000 +"
b0 *"
b11001000 )"
b10000000 @
b10000000 h
b10000000 x
b10000000 <
b10000000 \
b10000000 y
b10000000 8
b10000000 D
b10000000 z
b11001000 }
b11001000 |
b11001000 {
1"
#1200000
0"
b1010 *
b1010 3
b1010 -"
b1010 )
b1010 2
b1010 ,"
b1010 '
b1010 0
b1010 !"
b1010 &
b1010 /
b1010 ~
b1010 $
b1010 -
b1010 s
b1010 #
b1010 ,
b1010 r
