Comparator_8bits.v
module Comparator_8bits(Max, Min, A, B/*, clk*/);
    //input             clk;
    input       [7:0] A, B;
    output      [7:0] Max, Min;

    // always @(posedge clk) begin
    //     Max <= (A > B) ? A : B;
    //     Min <= (A < B) ? A : B;
    // end

    assign Max = (A > B) ? A : B;
    assign Min = (A < B) ? A : B;
endmodule

Ascending_Sorter_3inputs_8bits.v
//`include "Comparator_8bits.v"

module Ascending_Sorter_3inputs_8bits(min, mid, max, 
                                      in0, in1, in2,
                                      clk);
    
    input   wire        clk;
    input   wire [7:0]  in0, in1, in2;
    output  reg  [7:0]  min, mid, max;

    //reg     [7:0] st0_buf[2:0]; // [0] <- max, [1] <- min, [2] <- in2

    wire    [7:0] wC0_Max, wC0_Min;
    wire    [7:0] wC1_Max, wC1_Min;
    wire    [7:0] wC2_Max, wC2_Min;

    reg     [7:0] State0_Buf[2:0];
    reg     [7:0] State1_Buf[2:0];



    Comparator_8bits C0(.Max(wC0_Max), .Min(wC0_Min),
                        .A(in0), .B(in1));

    Comparator_8bits C1(.Max(wC1_Max), .Min(wC1_Min),
                        .A(State0_Buf[0]), .B(State0_Buf[2]));

    Comparator_8bits C2(.Max(wC2_Max), .Min(wC2_Min),
                        .A(State1_Buf[1]), .B(State1_Buf[2]));

    always @(posedge clk) begin
        State0_Buf[0] <= wC0_Max;
        State0_Buf[1] <= wC0_Min;
        State0_Buf[2] <= in2;

        State1_Buf[0] <= wC1_Max;
        State1_Buf[1] <= wC1_Min;
        State1_Buf[2] <= State0_Buf[1];

        max <= State1_Buf[0];
        mid <= wC2_Max;
        min <= wC2_Min;

    end


    // always@(posedge clk) begin
    //     min <= (in0 < in1) ? ((in0 < in2) ? in0 : in2) : ((in1 < in2) ? in1 : in2);
    //     max <= (in0 > in1) ? ((in0 > in2) ? in0 : in2) : ((in1 > in2) ? in1 : in2);
    //     mid <= (in0 > in1) ? 
    //            ((in1 > in2) ? in1 : ((in0 > in2) ? in2 : in0)) : 
    //            ((in0 > in2) ? in0 : ((in1 > in2) ? in2 : in1));
    // end

    
endmodule

Median_Finder_9inputs_8bits.v
//`include "Ascending_Sorter_3inputs_8bits.v"

module Median_Finder_9inputs_8bits(
    output wire [7:0] median_pixel,
    input  wire [7:0] pixel0, pixel1, pixel2,
    input  wire [7:0] pixel3, pixel4, pixel5,
    input  wire [7:0] pixel6, pixel7, pixel8,
    input  wire       clk
);

    reg     [7:0] rmin0, rmid0, rmax0;
    reg     [7:0] rmin1, rmid1, rmax1;
    reg     [7:0] rmin2, rmid2, rmax2;
    
    wire    [7:0] wmin0, wmid0, wmax0;
    wire    [7:0] wmin1, wmid1, wmax1;
    wire    [7:0] wmin2, wmid2, wmax2;

    reg     [7:0] rmax_col0, rmid_col1, rmin_col2;
    wire    [7:0] wmax_col0, wmid_col1, wmin_col2;

    //STAGE 0
    Ascending_Sorter_3inputs_8bits Row0(
        .min(wmin0), .mid(wmid0), .max(wmax0),
        .in0(pixel0), .in1(pixel1), .in2(pixel2),
        .clk(clk)
    );

    Ascending_Sorter_3inputs_8bits Row1(
        .min(wmin1), .mid(wmid1), .max(wmax1),
        .in0(pixel3), .in1(pixel4), .in2(pixel5),
        .clk(clk)
    );

    Ascending_Sorter_3inputs_8bits Row2(
        .min(wmin2), .mid(wmid2), .max(wmax2),
        .in0(pixel6), .in1(pixel7), .in2(pixel8),
        .clk(clk)
    );


    //STAGE 1
    Ascending_Sorter_3inputs_8bits FindMax(
        .max(wmax_col0),
        .in0(rmin0), .in1(rmin1), .in2(rmin2),        
        .clk(clk)
    );

    Ascending_Sorter_3inputs_8bits FindMid(
        .mid(wmid_col1),
        .in0(rmid0), .in1(rmid1), .in2(rmid2),        
        .clk(clk)
    );

    Ascending_Sorter_3inputs_8bits FindMin(
        .min(wmin_col2),
        .in0(rmax0), .in1(rmax1), .in2(rmax2),        
        .clk(clk)
    );

    always @(posedge clk) begin
        rmin0 <= wmin0;
        rmid0 <= wmid0;
        rmax0 <= wmax0;

        rmin1 <= wmin1;
        rmid1 <= wmid1;
        rmax1 <= wmax1;

        rmin2 <= wmin2;
        rmid2 <= wmid2;
        rmax2 <= wmax2;

        rmax_col0 <= wmax_col0;
        rmid_col1 <= wmid_col1;
        rmin_col2 <= wmin_col2;
    end

    
    
    // assign max_col0 = (rmin0 > rmin1) ? ((rmin0 > rmin2) ? rmin0 : rmin2) : ((rmin1 > rmin2) ? rmin1 : rmin2);

    // assign mid_col1 = (rmid0 > rmid1) ? 
    //              ((rmid1 > rmid2) ? rmid1 : ((rmid0 > rmid2) ? rmid2 : rmid0)) : 
    //              ((rmid0 > rmid2) ? rmid0 : ((rmid1 > rmid2) ? rmid2 : rmid1));
        
    // assign min_col2 = (rmax0 < rmax1) ? ((rmax0 < rmax2) ? rmax0 : rmax2) : ((rmax1 < rmax2) ? rmax1 : rmax2);


    Ascending_Sorter_3inputs_8bits FindMedian(
        .mid(median_pixel),
        .in0(rmax_col0), .in1(rmid_col1), .in2(rmin_col2),
        .clk(clk)
    );

endmodule

tb_Median_Finder_9inputs_8bits.v
`timescale 10ns / 1ps
`include "Median_Finder_9inputs_8bits.v"

module tb_Median_Finder_9inputs_8bits;
    reg     [7:0] pixel0, pixel1, pixel2;
    reg     [7:0] pixel3, pixel4, pixel5;
    reg     [7:0] pixel6, pixel7, pixel8;
    reg           clk;
    wire    [7:0] median_pixel;

    Median_Finder_9inputs_8bits utt(
        .median_pixel(median_pixel),
        .pixel0(pixel0), .pixel1(pixel1), .pixel2(pixel2), 
        .pixel3(pixel3), .pixel4(pixel4), .pixel5(pixel5), 
        .pixel6(pixel6), .pixel7(pixel7), .pixel8(pixel8),
        .clk(clk)
    );

    initial begin
        clk = 0;
    end

    always #5 clk = ~clk;

    initial begin
        $dumpfile("tb_Median_Finder_9inputs_8bits.vcd");
        $dumpvars(0, tb_Median_Finder_9inputs_8bits);

        
        pixel0 = 8'd1; pixel1 = 8'd2; pixel2 = 8'd3;
        pixel3 = 8'd1; pixel4 = 8'd2; pixel5 = 8'd3;
        pixel6 = 8'd1; pixel7 = 8'd2; pixel8 = 8'd3;

        #10
        pixel0 = 8'd1; pixel1 = 8'd1; pixel2 = 8'd1;
        pixel3 = 8'd1; pixel4 = 8'd1; pixel5 = 8'd1;
        pixel6 = 8'd1; pixel7 = 8'd1; pixel8 = 8'd1;

        #10
        pixel0 = 8'd1; pixel1 = 8'd2; pixel2 = 8'd3;
        pixel3 = 8'd4; pixel4 = 8'd5; pixel5 = 8'd6;
        pixel6 = 8'd7; pixel7 = 8'd8; pixel8 = 8'd9;

        #10
        pixel0 = 8'd2; pixel1 = 8'd12; pixel2 = 8'd36;
        pixel3 = 8'd5; pixel4 = 8'd27; pixel5 = 8'd18;
        pixel6 = 8'd8; pixel7 = 8'd25; pixel8 = 8'd22;

        #10
        pixel0 = 8'd18; pixel1 = 8'd20; pixel2 = 8'd3;
        pixel3 = 8'd12; pixel4 = 8'd12; pixel5 = 8'd6;
        pixel6 = 8'd15; pixel7 = 8'd12; pixel8 = 8'd9;

        #10
        pixel0 = 8'd50; pixel1 = 8'd100; pixel2 = 8'd150;
        pixel3 = 8'd40; pixel4 = 8'd90; pixel5 = 8'd140;
        pixel6 = 8'd30; pixel7 = 8'd80; pixel8 = 8'd130;

        #10
        pixel0 = 8'd255; pixel1 = 8'd200; pixel2 = 8'd180;
        pixel3 = 8'd170; pixel4 = 8'd160; pixel5 = 8'd150;
        pixel6 = 8'd100; pixel7 = 8'd50; pixel8 = 8'd0;

        #10
        pixel0 = 8'd64; pixel1 = 8'd32; pixel2 = 8'd16;
        pixel3 = 8'd128; pixel4 = 8'd64; pixel5 = 8'd32;
        pixel6 = 8'd8; pixel7 = 8'd4; pixel8 = 8'd2;

        #10
        pixel0 = 8'd111; pixel1 = 8'd111; pixel2 = 8'd222;
        pixel3 = 8'd222; pixel4 = 8'd111; pixel5 = 8'd222;
        pixel6 = 8'd111; pixel7 = 8'd222; pixel8 = 8'd111;

        #10
        pixel0 = 8'd5; pixel1 = 8'd95; pixel2 = 8'd45;
        pixel3 = 8'd75; pixel4 = 8'd25; pixel5 = 8'd85;
        pixel6 = 8'd55; pixel7 = 8'd65; pixel8 = 8'd35;

        #50;
        $finish;
    end

endmodule

tb_Median_Finder_9inputs_8bits.vcd
$date
	Tue Dec 23 12:44:29 2025
$end
$version
	Icarus Verilog
$end
$timescale
	1ps
$end
$scope module tb_Median_Finder_9inputs_8bits $end
$var wire 8 ! median_pixel [7:0] $end
$var reg 1 " clk $end
$var reg 8 # pixel0 [7:0] $end
$var reg 8 $ pixel1 [7:0] $end
$var reg 8 % pixel2 [7:0] $end
$var reg 8 & pixel3 [7:0] $end
$var reg 8 ' pixel4 [7:0] $end
$var reg 8 ( pixel5 [7:0] $end
$var reg 8 ) pixel6 [7:0] $end
$var reg 8 * pixel7 [7:0] $end
$var reg 8 + pixel8 [7:0] $end
$scope module utt $end
$var wire 1 " clk $end
$var wire 8 , pixel0 [7:0] $end
$var wire 8 - pixel1 [7:0] $end
$var wire 8 . pixel2 [7:0] $end
$var wire 8 / pixel3 [7:0] $end
$var wire 8 0 pixel4 [7:0] $end
$var wire 8 1 pixel5 [7:0] $end
$var wire 8 2 pixel6 [7:0] $end
$var wire 8 3 pixel7 [7:0] $end
$var wire 8 4 pixel8 [7:0] $end
$var wire 8 5 wmin_col2 [7:0] $end
$var wire 8 6 wmin2 [7:0] $end
$var wire 8 7 wmin1 [7:0] $end
$var wire 8 8 wmin0 [7:0] $end
$var wire 8 9 wmid_col1 [7:0] $end
$var wire 8 : wmid2 [7:0] $end
$var wire 8 ; wmid1 [7:0] $end
$var wire 8 < wmid0 [7:0] $end
$var wire 8 = wmax_col0 [7:0] $end
$var wire 8 > wmax2 [7:0] $end
$var wire 8 ? wmax1 [7:0] $end
$var wire 8 @ wmax0 [7:0] $end
$var wire 8 A median_pixel [7:0] $end
$var reg 8 B rmax0 [7:0] $end
$var reg 8 C rmax1 [7:0] $end
$var reg 8 D rmax2 [7:0] $end
$var reg 8 E rmax_col0 [7:0] $end
$var reg 8 F rmid0 [7:0] $end
$var reg 8 G rmid1 [7:0] $end
$var reg 8 H rmid2 [7:0] $end
$var reg 8 I rmid_col1 [7:0] $end
$var reg 8 J rmin0 [7:0] $end
$var reg 8 K rmin1 [7:0] $end
$var reg 8 L rmin2 [7:0] $end
$var reg 8 M rmin_col2 [7:0] $end
$scope module FindMax $end
$var wire 1 " clk $end
$var wire 8 N in0 [7:0] $end
$var wire 8 O in1 [7:0] $end
$var wire 8 P in2 [7:0] $end
$var wire 8 Q wC2_Min [7:0] $end
$var wire 8 R wC2_Max [7:0] $end
$var wire 8 S wC1_Min [7:0] $end
$var wire 8 T wC1_Max [7:0] $end
$var wire 8 U wC0_Min [7:0] $end
$var wire 8 V wC0_Max [7:0] $end
$var reg 8 W max [7:0] $end
$var reg 8 X mid [7:0] $end
$var reg 8 Y min [7:0] $end
$scope module C0 $end
$var wire 8 Z A [7:0] $end
$var wire 8 [ B [7:0] $end
$var wire 8 \ Min [7:0] $end
$var wire 8 ] Max [7:0] $end
$upscope $end
$scope module C1 $end
$var wire 8 ^ A [7:0] $end
$var wire 8 _ B [7:0] $end
$var wire 8 ` Min [7:0] $end
$var wire 8 a Max [7:0] $end
$upscope $end
$scope module C2 $end
$var wire 8 b A [7:0] $end
$var wire 8 c B [7:0] $end
$var wire 8 d Min [7:0] $end
$var wire 8 e Max [7:0] $end
$upscope $end
$upscope $end
$scope module FindMedian $end
$var wire 1 " clk $end
$var wire 8 f in0 [7:0] $end
$var wire 8 g in1 [7:0] $end
$var wire 8 h in2 [7:0] $end
$var wire 8 i wC2_Min [7:0] $end
$var wire 8 j wC2_Max [7:0] $end
$var wire 8 k wC1_Min [7:0] $end
$var wire 8 l wC1_Max [7:0] $end
$var wire 8 m wC0_Min [7:0] $end
$var wire 8 n wC0_Max [7:0] $end
$var reg 8 o max [7:0] $end
$var reg 8 p mid [7:0] $end
$var reg 8 q min [7:0] $end
$scope module C0 $end
$var wire 8 r A [7:0] $end
$var wire 8 s B [7:0] $end
$var wire 8 t Min [7:0] $end
$var wire 8 u Max [7:0] $end
$upscope $end
$scope module C1 $end
$var wire 8 v A [7:0] $end
$var wire 8 w B [7:0] $end
$var wire 8 x Min [7:0] $end
$var wire 8 y Max [7:0] $end
$upscope $end
$scope module C2 $end
$var wire 8 z A [7:0] $end
$var wire 8 { B [7:0] $end
$var wire 8 | Min [7:0] $end
$var wire 8 } Max [7:0] $end
$upscope $end
$upscope $end
$scope module FindMid $end
$var wire 1 " clk $end
$var wire 8 ~ in0 [7:0] $end
$var wire 8 !" in1 [7:0] $end
$var wire 8 "" in2 [7:0] $end
$var wire 8 #" wC2_Min [7:0] $end
$var wire 8 $" wC2_Max [7:0] $end
$var wire 8 %" wC1_Min [7:0] $end
$var wire 8 &" wC1_Max [7:0] $end
$var wire 8 '" wC0_Min [7:0] $end
$var wire 8 (" wC0_Max [7:0] $end
$var reg 8 )" max [7:0] $end
$var reg 8 *" mid [7:0] $end
$var reg 8 +" min [7:0] $end
$scope module C0 $end
$var wire 8 ," A [7:0] $end
$var wire 8 -" B [7:0] $end
$var wire 8 ." Min [7:0] $end
$var wire 8 /" Max [7:0] $end
$upscope $end
$scope module C1 $end
$var wire 8 0" A [7:0] $end
$var wire 8 1" B [7:0] $end
$var wire 8 2" Min [7:0] $end
$var wire 8 3" Max [7:0] $end
$upscope $end
$scope module C2 $end
$var wire 8 4" A [7:0] $end
$var wire 8 5" B [7:0] $end
$var wire 8 6" Min [7:0] $end
$var wire 8 7" Max [7:0] $end
$upscope $end
$upscope $end
$scope module FindMin $end
$var wire 1 " clk $end
$var wire 8 8" in0 [7:0] $end
$var wire 8 9" in1 [7:0] $end
$var wire 8 :" in2 [7:0] $end
$var wire 8 ;" wC2_Min [7:0] $end
$var wire 8 <" wC2_Max [7:0] $end
$var wire 8 =" wC1_Min [7:0] $end
$var wire 8 >" wC1_Max [7:0] $end
$var wire 8 ?" wC0_Min [7:0] $end
$var wire 8 @" wC0_Max [7:0] $end
$var reg 8 A" max [7:0] $end
$var reg 8 B" mid [7:0] $end
$var reg 8 C" min [7:0] $end
$scope module C0 $end
$var wire 8 D" A [7:0] $end
$var wire 8 E" B [7:0] $end
$var wire 8 F" Min [7:0] $end
$var wire 8 G" Max [7:0] $end
$upscope $end
$scope module C1 $end
$var wire 8 H" A [7:0] $end
$var wire 8 I" B [7:0] $end
$var wire 8 J" Min [7:0] $end
$var wire 8 K" Max [7:0] $end
$upscope $end
$scope module C2 $end
$var wire 8 L" A [7:0] $end
$var wire 8 M" B [7:0] $end
$var wire 8 N" Min [7:0] $end
$var wire 8 O" Max [7:0] $end
$upscope $end
$upscope $end
$scope module Row0 $end
$var wire 1 " clk $end
$var wire 8 P" in0 [7:0] $end
$var wire 8 Q" in1 [7:0] $end
$var wire 8 R" in2 [7:0] $end
$var wire 8 S" wC2_Min [7:0] $end
$var wire 8 T" wC2_Max [7:0] $end
$var wire 8 U" wC1_Min [7:0] $end
$var wire 8 V" wC1_Max [7:0] $end
$var wire 8 W" wC0_Min [7:0] $end
$var wire 8 X" wC0_Max [7:0] $end
$var reg 8 Y" max [7:0] $end
$var reg 8 Z" mid [7:0] $end
$var reg 8 [" min [7:0] $end
$scope module C0 $end
$var wire 8 \" A [7:0] $end
$var wire 8 ]" B [7:0] $end
$var wire 8 ^" Min [7:0] $end
$var wire 8 _" Max [7:0] $end
$upscope $end
$scope module C1 $end
$var wire 8 `" A [7:0] $end
$var wire 8 a" B [7:0] $end
$var wire 8 b" Min [7:0] $end
$var wire 8 c" Max [7:0] $end
$upscope $end
$scope module C2 $end
$var wire 8 d" A [7:0] $end
$var wire 8 e" B [7:0] $end
$var wire 8 f" Min [7:0] $end
$var wire 8 g" Max [7:0] $end
$upscope $end
$upscope $end
$scope module Row1 $end
$var wire 1 " clk $end
$var wire 8 h" in0 [7:0] $end
$var wire 8 i" in1 [7:0] $end
$var wire 8 j" in2 [7:0] $end
$var wire 8 k" wC2_Min [7:0] $end
$var wire 8 l" wC2_Max [7:0] $end
$var wire 8 m" wC1_Min [7:0] $end
$var wire 8 n" wC1_Max [7:0] $end
$var wire 8 o" wC0_Min [7:0] $end
$var wire 8 p" wC0_Max [7:0] $end
$var reg 8 q" max [7:0] $end
$var reg 8 r" mid [7:0] $end
$var reg 8 s" min [7:0] $end
$scope module C0 $end
$var wire 8 t" A [7:0] $end
$var wire 8 u" B [7:0] $end
$var wire 8 v" Min [7:0] $end
$var wire 8 w" Max [7:0] $end
$upscope $end
$scope module C1 $end
$var wire 8 x" A [7:0] $end
$var wire 8 y" B [7:0] $end
$var wire 8 z" Min [7:0] $end
$var wire 8 {" Max [7:0] $end
$upscope $end
$scope module C2 $end
$var wire 8 |" A [7:0] $end
$var wire 8 }" B [7:0] $end
$var wire 8 ~" Min [7:0] $end
$var wire 8 !# Max [7:0] $end
$upscope $end
$upscope $end
$scope module Row2 $end
$var wire 1 " clk $end
$var wire 8 "# in0 [7:0] $end
$var wire 8 ## in1 [7:0] $end
$var wire 8 $# in2 [7:0] $end
$var wire 8 %# wC2_Min [7:0] $end
$var wire 8 &# wC2_Max [7:0] $end
$var wire 8 '# wC1_Min [7:0] $end
$var wire 8 (# wC1_Max [7:0] $end
$var wire 8 )# wC0_Min [7:0] $end
$var wire 8 *# wC0_Max [7:0] $end
$var reg 8 +# max [7:0] $end
$var reg 8 ,# mid [7:0] $end
$var reg 8 -# min [7:0] $end
$scope module C0 $end
$var wire 8 .# A [7:0] $end
$var wire 8 /# B [7:0] $end
$var wire 8 0# Min [7:0] $end
$var wire 8 1# Max [7:0] $end
$upscope $end
$scope module C1 $end
$var wire 8 2# A [7:0] $end
$var wire 8 3# B [7:0] $end
$var wire 8 4# Min [7:0] $end
$var wire 8 5# Max [7:0] $end
$upscope $end
$scope module C2 $end
$var wire 8 6# A [7:0] $end
$var wire 8 7# B [7:0] $end
$var wire 8 8# Min [7:0] $end
$var wire 8 9# Max [7:0] $end
$upscope $end
$upscope $end
$upscope $end
$upscope $end
$enddefinitions $end
$comment Show the parameter values. $end
$dumpall
$end
#0
$dumpvars
bx 9#
bx 8#
bx 7#
bx 6#
bx 5#
bx 4#
bx 3#
bx 2#
b10 1#
b1 0#
b10 /#
b1 .#
bx -#
bx ,#
bx +#
b10 *#
b1 )#
bx (#
bx '#
bx &#
bx %#
b11 $#
b10 ##
b1 "#
bx !#
bx ~"
bx }"
bx |"
bx {"
bx z"
bx y"
bx x"
b10 w"
b1 v"
b10 u"
b1 t"
bx s"
bx r"
bx q"
b10 p"
b1 o"
bx n"
bx m"
bx l"
bx k"
b11 j"
b10 i"
b1 h"
bx g"
bx f"
bx e"
bx d"
bx c"
bx b"
bx a"
bx `"
b10 _"
b1 ^"
b10 ]"
b1 \"
bx ["
bx Z"
bx Y"
b10 X"
b1 W"
bx V"
bx U"
bx T"
bx S"
b11 R"
b10 Q"
b1 P"
bx O"
bx N"
bx M"
bx L"
bx K"
bx J"
bx I"
bx H"
bx G"
bx F"
bx E"
bx D"
bx C"
bx B"
bx A"
bx @"
bx ?"
bx >"
bx ="
bx <"
bx ;"
bx :"
bx 9"
bx 8"
bx 7"
bx 6"
bx 5"
bx 4"
bx 3"
bx 2"
bx 1"
bx 0"
bx /"
bx ."
bx -"
bx ,"
bx +"
bx *"
bx )"
bx ("
bx '"
bx &"
bx %"
bx $"
bx #"
bx ""
bx !"
bx ~
bx }
bx |
bx {
bx z
bx y
bx x
bx w
bx v
bx u
bx t
bx s
bx r
bx q
bx p
bx o
bx n
bx m
bx l
bx k
bx j
bx i
bx h
bx g
bx f
bx e
bx d
bx c
bx b
bx a
bx `
bx _
bx ^
bx ]
bx \
bx [
bx Z
bx Y
bx X
bx W
bx V
bx U
bx T
bx S
bx R
bx Q
bx P
bx O
bx N
bx M
bx L
bx K
bx J
bx I
bx H
bx G
bx F
bx E
bx D
bx C
bx B
bx A
bx @
bx ?
bx >
bx =
bx <
bx ;
bx :
bx 9
bx 8
bx 7
bx 6
bx 5
b11 4
b10 3
b1 2
b11 1
b10 0
b1 /
b11 .
b10 -
b1 ,
b11 +
b10 *
b1 )
b11 (
b10 '
b1 &
b11 %
b10 $
b1 #
0"
bx !
$end
#50000
b11 V"
b11 c"
b10 U"
b10 b"
b11 n"
b11 {"
b10 m"
b10 z"
b11 (#
b11 5#
b10 '#
b10 4#
b11 a"
b10 `"
b11 y"
b10 x"
b11 3#
b10 2#
1"
#100000
b1 *#
b1 1#
b1 p"
b1 w"
b1 X"
b1 _"
0"
b1 +
b1 4
b1 $#
b1 *
b1 3
b1 ##
b1 /#
b1 (
b1 1
b1 j"
b1 '
b1 0
b1 i"
b1 u"
b1 %
b1 .
b1 R"
b1 $
b1 -
b1 Q"
b1 ]"
#150000
b10 &#
b10 9#
b1 %#
b1 8#
b1 (#
b1 5#
b1 '#
b1 4#
b10 l"
b10 !#
b1 k"
b1 ~"
b1 n"
b1 {"
b1 m"
b1 z"
b10 T"
b10 g"
b1 S"
b1 f"
b1 V"
b1 c"
b1 U"
b1 b"
b1 7#
b10 6#
b1 3#
b1 2#
b1 }"
b10 |"
b1 y"
b1 x"
b1 e"
b10 d"
b1 a"
b1 `"
1"
#200000
b111 )#
b111 0#
b1000 *#
b1000 1#
b100 o"
b100 v"
b101 p"
b101 w"
b10 X"
b10 _"
0"
b1001 +
b1001 4
b1001 $#
b1000 *
b1000 3
b1000 ##
b1000 /#
b111 )
b111 2
b111 "#
b111 .#
b110 (
b110 1
b110 j"
b101 '
b101 0
b101 i"
b101 u"
b100 &
b100 /
b100 h"
b100 t"
b11 %
b11 .
b11 R"
b10 $
b10 -
b10 Q"
b10 ]"
#250000
b1 T"
b1 g"
b10 U"
b10 b"
b11 V"
b11 c"
b1 l"
b1 !#
b101 m"
b101 z"
b110 n"
b110 {"
b1 &#
b1 9#
b1000 '#
b1000 4#
b1001 (#
b1001 5#
b1 8
b1 ["
b10 <
b10 Z"
b11 @
b11 Y"
b1 d"
b11 a"
b10 `"
b1 7
b1 s"
b10 ;
b10 r"
b11 ?
b11 q"
b1 |"
b110 y"
b101 x"
b1 6
b1 -#
b10 :
b10 ,#
b11 >
b11 +#
b1 6#
b1001 3#
b1000 2#
1"
#300000
b11001 *#
b11001 1#
b1000 )#
b1000 0#
b11011 p"
b11011 w"
b101 o"
b101 v"
b1100 X"
b1100 _"
b10 W"
b10 ^"
0"
b10110 +
b10110 4
b10110 $#
b11001 *
b11001 3
b11001 ##
b11001 /#
b1000 )
b1000 2
b1000 "#
b1000 .#
b10010 (
b10010 1
b10010 j"
b11011 '
b11011 0
b11011 i"
b11011 u"
b101 &
b101 /
b101 h"
b101 t"
b100100 %
b100100 .
b100100 R"
b1100 $
b1100 -
b1100 Q"
b1100 ]"
b10 #
b10 ,
b10 P"
b10 \"
#350000
b11 @"
b11 G"
b11 ?"
b11 F"
b10 ("
b10 /"
b10 '"
b10 ."
b1 V
b1 ]
b1 U
b1 \
b111 %#
b111 8#
b1000 &#
b1000 9#
b11001 (#
b11001 5#
b10110 '#
b10110 4#
b100 k"
b100 ~"
b101 l"
b101 !#
b11011 n"
b11011 {"
b10010 m"
b10010 z"
b10 T"
b10 g"
b100100 V"
b100100 c"
b1100 U"
b1100 b"
b11 D
b11 :"
b10 H
b10 ""
b1 L
b1 P
b11 C
b11 9"
b11 E"
b10 G
b10 !"
b10 -"
b1 K
b1 O
b1 [
b11 B
b11 8"
b11 D"
b10 F
b10 ~
b10 ,"
b1 J
b1 N
b1 Z
b1 :
b1 ,#
b1 >
b1 +#
b111 7#
b1000 6#
b10110 3#
b11001 2#
b1 ;
b1 r"
b1 ?
b1 q"
b100 }"
b101 |"
b10010 y"
b11011 x"
b1 <
b1 Z"
b1 @
b1 Y"
b10 d"
b100100 a"
b1100 `"
1"
#400000
b1111 *#
b1111 1#
b1100 )#
b1100 0#
b1100 p"
b1100 w"
b1100 o"
b1100 v"
b10100 X"
b10100 _"
b10010 W"
b10010 ^"
0"
b1001 +
b1001 4
b1001 $#
b1100 *
b1100 3
b1100 ##
b1100 /#
b1111 )
b1111 2
b1111 "#
b1111 .#
b110 (
b110 1
b110 j"
b1100 '
b1100 0
b1100 i"
b1100 u"
b1100 &
b1100 /
b1100 h"
b1100 t"
b11 %
b11 .
b11 R"
b10100 $
b10100 -
b10100 Q"
b10100 ]"
b10010 #
b10010 ,
b10010 P"
b10010 \"
#450000
b10 S"
b10 f"
b1100 T"
b1100 g"
b10100 V"
b10100 c"
b11 U"
b11 b"
b101 k"
b101 ~"
b10010 l"
b10010 !#
b1100 n"
b1100 {"
b110 m"
b110 z"
b1000 %#
b1000 8#
b10110 &#
b10110 9#
b1111 (#
b1111 5#
b1001 '#
b1001 4#
b1 T
b1 a
b1 S
b1 `
b10 &"
b10 3"
b10 %"
b10 2"
b11 >"
b11 K"
b11 ="
b11 J"
b1 @"
b1 G"
b1 ("
b1 /"
b1 ?"
b1 F"
b1 '"
b1 ."
b10 <
b10 Z"
b11 @
b11 Y"
b10 e"
b1100 d"
b11 a"
b10100 `"
b100 7
b100 s"
b101 ;
b101 r"
b110 ?
b110 q"
b101 }"
b10010 |"
b110 y"
b1100 x"
b111 6
b111 -#
b1000 :
b1000 ,#
b1001 >
b1001 +#
b1000 7#
b10110 6#
b1001 3#
b1111 2#
b1 _
b1 ^
b10 1"
b10 0"
b11 I"
b11 H"
b1 D
b1 :"
b1 H
b1 ""
b1 C
b1 9"
b1 E"
b1 G
b1 !"
b1 -"
b1 B
b1 8"
b1 D"
b1 F
b1 ~
b1 ,"
1"
#500000
b11110 )#
b11110 0#
b1010000 *#
b1010000 1#
b101000 o"
b101000 v"
b1011010 p"
b1011010 w"
b1100100 X"
b1100100 _"
b110010 W"
b110010 ^"
0"
b10000010 +
b10000010 4
b10000010 $#
b1010000 *
b1010000 3
b1010000 ##
b1010000 /#
b11110 )
b11110 2
b11110 "#
b11110 .#
b10001100 (
b10001100 1
b10001100 j"
b1011010 '
b1011010 0
b1011010 i"
b1011010 u"
b101000 &
b101000 /
b101000 h"
b101000 t"
b10010110 %
b10010110 .
b10010110 R"
b1100100 $
b1100100 -
b1100100 Q"
b1100100 ]"
b110010 #
b110010 ,
b110010 P"
b110010 \"
#550000
b11 ?"
b11 F"
b10 '"
b10 ."
b100 V
b100 ]
b110 @"
b110 G"
b101 ("
b101 /"
b11 <"
b11 O"
b11 ;"
b11 N"
b1 >"
b1 K"
b1 ="
b1 J"
b10 $"
b10 7"
b10 #"
b10 6"
b1 &"
b1 3"
b1 %"
b1 2"
b1 R
b1 e
b1 Q
b1 d
b1001 %#
b1001 8#
b1100 &#
b1100 9#
b1010000 '#
b1010000 4#
b10000010 (#
b10000010 5#
b110 k"
b110 ~"
b1100 l"
b1100 !#
b1011010 m"
b1011010 z"
b10001100 n"
b10001100 {"
b11 S"
b11 f"
b10010 T"
b10010 g"
b1100100 U"
b1100100 b"
b10010110 V"
b10010110 c"
b1001 D
b1001 :"
b1000 H
b1000 ""
b111 L
b111 P
b110 C
b110 9"
b110 E"
b101 G
b101 !"
b101 -"
b100 K
b100 O
b100 [
b11 B
b11 8"
b11 D"
b10 F
b10 ~
b10 ,"
b11 M"
b11 L"
b1 I"
b1 H"
b10 5"
b10 4"
b1 1"
b1 0"
b1 c
b1 b
b1000 6
b1000 -#
b10110 :
b10110 ,#
b11001 >
b11001 +#
b1100 7#
b1001 6#
b10000010 3#
b1010000 2#
b101 7
b101 s"
b10010 ;
b10010 r"
b11011 ?
b11011 q"
b1100 }"
b110 |"
b10001100 y"
b1011010 x"
b10 8
b10 ["
b1100 <
b1100 Z"
b100100 @
b100100 Y"
b10010 e"
b11 d"
b10010110 a"
b1100100 `"
1"
#600000
b1100100 *#
b1100100 1#
b110010 )#
b110010 0#
b10101010 p"
b10101010 w"
b10100000 o"
b10100000 v"
b11111111 X"
b11111111 _"
b11001000 W"
b11001000 ^"
0"
b0 +
b0 4
b0 $#
b110010 *
b110010 3
b110010 ##
b110010 /#
b1100100 )
b1100100 2
b1100100 "#
b1100100 .#
b10010110 (
b10010110 1
b10010110 j"
b10100000 '
b10100000 0
b10100000 i"
b10100000 u"
b10101010 &
b10101010 /
b10101010 h"
b10101010 t"
b10110100 %
b10110100 .
b10110100 R"
b11001000 $
b11001000 -
b11001000 Q"
b11001000 ]"
b11111111 #
b11111111 ,
b11111111 P"
b11111111 \"
