Comparator_8bits.v
module Comparator_8bits(Max, Min, A, B/*, clk*/);
    //input             clk;
    input       [7:0] A, B;
    output      [7:0] Max, Min;

    // always @(posedge clk) begin
    //     Max <= (A > B) ? A : B;
    //     Min <= (A < B) ? A : B;
    // end

    assign Max = (A > B) ? A : B;
    assign Min = (A < B) ? A : B;
endmodule

Ascending_Sorter_3inputs_8bits.v
//`include "Comparator_8bits.v"

module Ascending_Sorter_3inputs_8bits(min, mid, max, 
                                      in0, in1, in2,
                                      clk);
    
    input   wire        clk;
    input   wire [7:0]  in0, in1, in2;
    output  reg  [7:0]  min, mid, max;

    //reg     [7:0] rin0, rin1, rin2;
    wire cmp0, cmp1, cmp2;  //0: in0 < in1?; 1:in1 < in2?; in0 < in2? 

    assign cmp0 = (in0 < in1);
    assign cmp1 = (in1 < in2);
    assign cmp2 = (in2 < in0);

    always @(posedge clk) begin
        if (cmp0) begin
            if (cmp2) begin
                min <= in2;
                mid <= in0;
                max <= in1;
            end
            else begin
                min <= in0;
                if (cmp1) begin
                    max <= in2;
                    mid <= in1;
                end
                else begin
                    max <= in1;
                    mid <= in2;
                end
            end
        end
        else begin
            if (cmp1) begin
                min <= in1;
                if (cmp2) begin
                    mid <= in2;
                    max <= in0;
                end
                else begin
                    mid <= in0;
                    max <= in2;
                end
            end
            else begin
                min <= in2;
                mid <= in1;
                max <= in0;
            end
        end
    end 

endmodule

Median_Finder_9inputs_8bits.v
//`include "Ascending_Sorter_3inputs_8bits.v"

module Median_Finder_9inputs_8bits(
    output wire [7:0] median_pixel,
    input  wire [7:0] pixel0, pixel1, pixel2,
    input  wire [7:0] pixel3, pixel4, pixel5,
    input  wire [7:0] pixel6, pixel7, pixel8,
    input  wire       clk
);

    // reg     [7:0] rmin0, rmid0, rmax0;
    // reg     [7:0] rmin1, rmid1, rmax1;
    // reg     [7:0] rmin2, rmid2, rmax2;
    
    wire    [7:0] wmin0, wmid0, wmax0;
    wire    [7:0] wmin1, wmid1, wmax1;
    wire    [7:0] wmin2, wmid2, wmax2;

    //reg     [7:0] rmax_col0, rmid_col1, rmin_col2;
    wire    [7:0] wmax_col0, wmid_col1, wmin_col2;

    //STAGE 0
    Ascending_Sorter_3inputs_8bits Row0(
        .min(wmin0), .mid(wmid0), .max(wmax0),
        .in0(pixel0), .in1(pixel1), .in2(pixel2),
        .clk(clk)
    );

    Ascending_Sorter_3inputs_8bits Row1(
        .min(wmin1), .mid(wmid1), .max(wmax1),
        .in0(pixel3), .in1(pixel4), .in2(pixel5),
        .clk(clk)
    );

    Ascending_Sorter_3inputs_8bits Row2(
        .min(wmin2), .mid(wmid2), .max(wmax2),
        .in0(pixel6), .in1(pixel7), .in2(pixel8),
        .clk(clk)
    );


    //STAGE 1
    Ascending_Sorter_3inputs_8bits FindMax(
        .max(wmax_col0),
        .in0(wmin0), .in1(wmin1), .in2(wmin2),        
        .clk(clk)
    );

    Ascending_Sorter_3inputs_8bits FindMid(
        .mid(wmid_col1),
        .in0(wmid0), .in1(wmid1), .in2(wmid2),        
        .clk(clk)
    );

    Ascending_Sorter_3inputs_8bits FindMin(
        .min(wmin_col2),
        .in0(wmax0), .in1(wmax1), .in2(wmax2),        
        .clk(clk)
    );

    // always @(posedge clk) begin
    //     rmin0 <= wmin0;
    //     rmid0 <= wmid0;
    //     rmax0 <= wmax0;

    //     rmin1 <= wmin1;
    //     rmid1 <= wmid1;
    //     rmax1 <= wmax1;

    //     rmin2 <= wmin2;
    //     rmid2 <= wmid2;
    //     rmax2 <= wmax2;

    //     rmax_col0 <= wmax_col0;
    //     rmid_col1 <= wmid_col1;
    //     rmin_col2 <= wmin_col2;
    // end

    
    
    // assign max_col0 = (rmin0 > rmin1) ? ((rmin0 > rmin2) ? rmin0 : rmin2) : ((rmin1 > rmin2) ? rmin1 : rmin2);

    // assign mid_col1 = (rmid0 > rmid1) ? 
    //              ((rmid1 > rmid2) ? rmid1 : ((rmid0 > rmid2) ? rmid2 : rmid0)) : 
    //              ((rmid0 > rmid2) ? rmid0 : ((rmid1 > rmid2) ? rmid2 : rmid1));
        
    // assign min_col2 = (rmax0 < rmax1) ? ((rmax0 < rmax2) ? rmax0 : rmax2) : ((rmax1 < rmax2) ? rmax1 : rmax2);


    Ascending_Sorter_3inputs_8bits FindMedian(
        .mid(median_pixel),
        .in0(wmax_col0), .in1(wmid_col1), .in2(wmin_col2),
        .clk(clk)
    );

endmodule

tb_Median_Finder_9inputs_8bits.v
`timescale 10ns / 1ps
`include "Median_Finder_9inputs_8bits.v"

module tb_Median_Finder_9inputs_8bits;
    reg     [7:0] pixel0, pixel1, pixel2;
    reg     [7:0] pixel3, pixel4, pixel5;
    reg     [7:0] pixel6, pixel7, pixel8;
    reg           clk;
    wire    [7:0] median_pixel;

    Median_Finder_9inputs_8bits utt(
        .median_pixel(median_pixel),
        .pixel0(pixel0), .pixel1(pixel1), .pixel2(pixel2), 
        .pixel3(pixel3), .pixel4(pixel4), .pixel5(pixel5), 
        .pixel6(pixel6), .pixel7(pixel7), .pixel8(pixel8),
        .clk(clk)
    );

    initial begin
        clk = 0;
    end

    always #5 clk = ~clk;

    initial begin
        $dumpfile("tb_Median_Finder_9inputs_8bits.vcd");
        $dumpvars(0, tb_Median_Finder_9inputs_8bits);

        
        pixel0 = 8'd1; pixel1 = 8'd2; pixel2 = 8'd3;
        pixel3 = 8'd1; pixel4 = 8'd2; pixel5 = 8'd3;
        pixel6 = 8'd1; pixel7 = 8'd2; pixel8 = 8'd3;

        #10
        pixel0 = 8'd1; pixel1 = 8'd1; pixel2 = 8'd1;
        pixel3 = 8'd1; pixel4 = 8'd1; pixel5 = 8'd1;
        pixel6 = 8'd1; pixel7 = 8'd1; pixel8 = 8'd1;

        #10
        pixel0 = 8'd1; pixel1 = 8'd2; pixel2 = 8'd3;
        pixel3 = 8'd4; pixel4 = 8'd5; pixel5 = 8'd6;
        pixel6 = 8'd7; pixel7 = 8'd8; pixel8 = 8'd9;

        #10
        pixel0 = 8'd2; pixel1 = 8'd12; pixel2 = 8'd36;
        pixel3 = 8'd5; pixel4 = 8'd27; pixel5 = 8'd18;
        pixel6 = 8'd8; pixel7 = 8'd25; pixel8 = 8'd22;

        #10
        pixel0 = 8'd18; pixel1 = 8'd20; pixel2 = 8'd3;
        pixel3 = 8'd12; pixel4 = 8'd12; pixel5 = 8'd6;
        pixel6 = 8'd15; pixel7 = 8'd12; pixel8 = 8'd9;

        #10
        pixel0 = 8'd50; pixel1 = 8'd100; pixel2 = 8'd150;
        pixel3 = 8'd40; pixel4 = 8'd90; pixel5 = 8'd140;
        pixel6 = 8'd30; pixel7 = 8'd80; pixel8 = 8'd130;

        #10
        pixel0 = 8'd255; pixel1 = 8'd200; pixel2 = 8'd180;
        pixel3 = 8'd170; pixel4 = 8'd160; pixel5 = 8'd150;
        pixel6 = 8'd100; pixel7 = 8'd50; pixel8 = 8'd0;

        #10
        pixel0 = 8'd64; pixel1 = 8'd32; pixel2 = 8'd16;
        pixel3 = 8'd128; pixel4 = 8'd64; pixel5 = 8'd32;
        pixel6 = 8'd8; pixel7 = 8'd4; pixel8 = 8'd2;

        #10
        pixel0 = 8'd111; pixel1 = 8'd111; pixel2 = 8'd222;
        pixel3 = 8'd222; pixel4 = 8'd111; pixel5 = 8'd222;
        pixel6 = 8'd111; pixel7 = 8'd222; pixel8 = 8'd111;

        #10
        pixel0 = 8'd5; pixel1 = 8'd95; pixel2 = 8'd45;
        pixel3 = 8'd75; pixel4 = 8'd25; pixel5 = 8'd85;
        pixel6 = 8'd55; pixel7 = 8'd65; pixel8 = 8'd35;

        #50;
        $finish;
    end

endmodule

tb_Median_Finder_9inputs_8bits.vcd
$date
	Wed Dec 24 21:36:18 2025
$end
$version
	Icarus Verilog
$end
$timescale
	1ps
$end
$scope module tb_Median_Finder_9inputs_8bits $end
$var wire 8 ! median_pixel [7:0] $end
$var reg 1 " clk $end
$var reg 8 # pixel0 [7:0] $end
$var reg 8 $ pixel1 [7:0] $end
$var reg 8 % pixel2 [7:0] $end
$var reg 8 & pixel3 [7:0] $end
$var reg 8 ' pixel4 [7:0] $end
$var reg 8 ( pixel5 [7:0] $end
$var reg 8 ) pixel6 [7:0] $end
$var reg 8 * pixel7 [7:0] $end
$var reg 8 + pixel8 [7:0] $end
$scope module utt $end
$var wire 1 " clk $end
$var wire 8 , pixel0 [7:0] $end
$var wire 8 - pixel1 [7:0] $end
$var wire 8 . pixel2 [7:0] $end
$var wire 8 / pixel3 [7:0] $end
$var wire 8 0 pixel4 [7:0] $end
$var wire 8 1 pixel5 [7:0] $end
$var wire 8 2 pixel6 [7:0] $end
$var wire 8 3 pixel7 [7:0] $end
$var wire 8 4 pixel8 [7:0] $end
$var wire 8 5 wmin_col2 [7:0] $end
$var wire 8 6 wmin2 [7:0] $end
$var wire 8 7 wmin1 [7:0] $end
$var wire 8 8 wmin0 [7:0] $end
$var wire 8 9 wmid_col1 [7:0] $end
$var wire 8 : wmid2 [7:0] $end
$var wire 8 ; wmid1 [7:0] $end
$var wire 8 < wmid0 [7:0] $end
$var wire 8 = wmax_col0 [7:0] $end
$var wire 8 > wmax2 [7:0] $end
$var wire 8 ? wmax1 [7:0] $end
$var wire 8 @ wmax0 [7:0] $end
$var wire 8 A median_pixel [7:0] $end
$scope module FindMax $end
$var wire 1 " clk $end
$var wire 8 B in2 [7:0] $end
$var wire 8 C in1 [7:0] $end
$var wire 8 D in0 [7:0] $end
$var wire 1 E cmp2 $end
$var wire 1 F cmp1 $end
$var wire 1 G cmp0 $end
$var reg 8 H max [7:0] $end
$var reg 8 I mid [7:0] $end
$var reg 8 J min [7:0] $end
$upscope $end
$scope module FindMedian $end
$var wire 1 " clk $end
$var wire 8 K in0 [7:0] $end
$var wire 8 L in2 [7:0] $end
$var wire 8 M in1 [7:0] $end
$var wire 1 N cmp2 $end
$var wire 1 O cmp1 $end
$var wire 1 P cmp0 $end
$var reg 8 Q max [7:0] $end
$var reg 8 R mid [7:0] $end
$var reg 8 S min [7:0] $end
$upscope $end
$scope module FindMid $end
$var wire 1 " clk $end
$var wire 8 T in2 [7:0] $end
$var wire 8 U in1 [7:0] $end
$var wire 8 V in0 [7:0] $end
$var wire 1 W cmp2 $end
$var wire 1 X cmp1 $end
$var wire 1 Y cmp0 $end
$var reg 8 Z max [7:0] $end
$var reg 8 [ mid [7:0] $end
$var reg 8 \ min [7:0] $end
$upscope $end
$scope module FindMin $end
$var wire 1 " clk $end
$var wire 8 ] in2 [7:0] $end
$var wire 8 ^ in1 [7:0] $end
$var wire 8 _ in0 [7:0] $end
$var wire 1 ` cmp2 $end
$var wire 1 a cmp1 $end
$var wire 1 b cmp0 $end
$var reg 8 c max [7:0] $end
$var reg 8 d mid [7:0] $end
$var reg 8 e min [7:0] $end
$upscope $end
$scope module Row0 $end
$var wire 1 " clk $end
$var wire 8 f in0 [7:0] $end
$var wire 8 g in1 [7:0] $end
$var wire 8 h in2 [7:0] $end
$var wire 1 i cmp2 $end
$var wire 1 j cmp1 $end
$var wire 1 k cmp0 $end
$var reg 8 l max [7:0] $end
$var reg 8 m mid [7:0] $end
$var reg 8 n min [7:0] $end
$upscope $end
$scope module Row1 $end
$var wire 1 " clk $end
$var wire 8 o in0 [7:0] $end
$var wire 8 p in1 [7:0] $end
$var wire 8 q in2 [7:0] $end
$var wire 1 r cmp2 $end
$var wire 1 s cmp1 $end
$var wire 1 t cmp0 $end
$var reg 8 u max [7:0] $end
$var reg 8 v mid [7:0] $end
$var reg 8 w min [7:0] $end
$upscope $end
$scope module Row2 $end
$var wire 1 " clk $end
$var wire 8 x in0 [7:0] $end
$var wire 8 y in1 [7:0] $end
$var wire 8 z in2 [7:0] $end
$var wire 1 { cmp2 $end
$var wire 1 | cmp1 $end
$var wire 1 } cmp0 $end
$var reg 8 ~ max [7:0] $end
$var reg 8 !" mid [7:0] $end
$var reg 8 "" min [7:0] $end
$upscope $end
$upscope $end
$upscope $end
$enddefinitions $end
$comment Show the parameter values. $end
$dumpall
$end
#0
$dumpvars
bx ""
bx !"
bx ~
1}
1|
0{
b11 z
b10 y
b1 x
bx w
bx v
bx u
1t
1s
0r
b11 q
b10 p
b1 o
bx n
bx m
bx l
1k
1j
0i
b11 h
b10 g
b1 f
bx e
bx d
bx c
xb
xa
x`
bx _
bx ^
bx ]
bx \
bx [
bx Z
xY
xX
xW
bx V
bx U
bx T
bx S
bx R
bx Q
xP
xO
xN
bx M
bx L
bx K
bx J
bx I
bx H
xG
xF
xE
bx D
bx C
bx B
bx A
bx @
bx ?
bx >
bx =
bx <
bx ;
bx :
bx 9
bx 8
bx 7
bx 6
bx 5
b11 4
b10 3
b1 2
b11 1
b10 0
b1 /
b11 .
b10 -
b1 ,
b11 +
b10 *
b1 )
b11 (
b10 '
b1 &
b11 %
b10 $
b1 #
0"
bx !
$end
#50000
0W
0Y
b10 <
b10 V
b10 m
0`
0b
b11 @
b11 _
b11 l
0E
0G
b1 8
b1 D
b1 n
0X
b10 ;
b10 U
b10 v
0a
b11 ?
b11 ^
b11 u
0F
b1 7
b1 C
b1 w
b10 :
b10 T
b10 !"
b11 >
b11 ]
b11 ~
b1 6
b1 B
b1 ""
1"
#100000
0"
0|
b1 +
b1 4
b1 z
0}
b1 *
b1 3
b1 y
0s
b1 (
b1 1
b1 q
0t
b1 '
b1 0
b1 p
0j
b1 %
b1 .
b1 h
0k
b1 $
b1 -
b1 g
#150000
b11 c
b11 d
0N
1O
b11 5
b11 L
b11 e
b10 Z
1P
b10 9
b10 M
b10 [
b10 \
b1 =
b1 H
b1 K
b1 I
b1 J
b1 >
b1 ]
b1 ~
b1 :
b1 T
b1 !"
0a
b1 ?
b1 ^
b1 u
0X
b1 ;
b1 U
b1 v
0b
b1 @
b1 _
b1 l
0Y
b1 <
b1 V
b1 m
1"
#200000
0"
1|
b1001 +
b1001 4
b1001 z
1}
b1000 *
b1000 3
b1000 y
0{
b111 )
b111 2
b111 x
1s
b110 (
b110 1
b110 q
1t
b101 '
b101 0
b101 p
0r
b100 &
b100 /
b100 o
1j
b11 %
b11 .
b11 h
1k
b10 $
b10 -
b10 g
#250000
b10 <
b10 V
b10 m
b11 @
b11 _
b11 l
1Y
b101 ;
b101 U
b101 v
1b
b110 ?
b110 ^
b110 u
1G
b100 7
b100 C
b100 w
1X
b1000 :
b1000 T
b1000 !"
1a
b1001 >
b1001 ]
b1001 ~
1F
b111 6
b111 B
b111 ""
b1 Z
0P
b1 9
b1 M
b1 [
b1 \
b1 c
b1 d
0O
b1 5
b1 L
b1 e
b10 !
b10 A
b10 R
b11 Q
b1 S
1"
#300000
0"
b10110 +
b10110 4
b10110 z
0|
b11001 *
b11001 3
b11001 y
1}
b1000 )
b1000 2
b1000 x
b10010 (
b10010 1
b10010 q
0s
b11011 '
b11011 0
b11011 p
1t
b101 &
b101 /
b101 o
b100100 %
b100100 .
b100100 h
1j
b1100 $
b1100 -
b1100 g
1k
b10 #
b10 ,
b10 f
#350000
b1 Q
b1 !
b1 A
b1 R
b110 d
b1001 c
b11 5
b11 L
b11 e
b101 9
b101 M
b101 [
b1000 Z
b10 \
b100 I
1N
b111 =
b111 H
b111 K
b10110 :
b10110 T
b10110 !"
b11001 >
b11001 ]
b11001 ~
b1000 6
b1000 B
b1000 ""
1X
b10010 ;
b10010 U
b10010 v
0a
b11011 ?
b11011 ^
b11011 u
b101 7
b101 C
b101 w
0W
1Y
b1100 <
b1100 V
b1100 m
1`
0b
b100100 @
b100100 _
b100100 l
b10 8
b10 D
b10 n
1"
#400000
0"
1{
b1001 +
b1001 4
b1001 z
0}
0|
b1100 *
b1100 3
b1100 y
b1111 )
b1111 2
b1111 x
1r
b110 (
b110 1
b110 q
0t
0s
b1100 '
b1100 0
b1100 p
b1100 &
b1100 /
b1100 o
0j
1i
b11 %
b11 .
b11 h
b10100 $
b10100 -
b10100 g
1k
b10010 #
b10010 ,
b10010 f
#450000
b10100 @
b10100 _
b10100 l
1W
b10010 <
b10010 V
b10010 m
b11 8
b11 D
b11 n
1a
b1100 ?
b1100 ^
b1100 u
0Y
b1100 ;
b1100 U
b1100 v
b110 7
b110 C
b110 w
b1111 >
b1111 ]
b1111 ~
0X
b1100 :
b1100 T
b1100 !"
b1001 6
b1001 B
b1001 ""
b101 I
b1000 =
b1000 H
b1000 K
b10 J
1P
b10010 9
b10010 M
b10010 [
b10110 Z
b1100 \
b100100 c
b11011 d
0N
1O
b11001 5
b11001 L
b11001 e
b111 Q
b101 !
b101 A
b101 R
b11 S
1"
#500000
0"
1|
0{
b10000010 +
b10000010 4
b10000010 z
1}
b1010000 *
b1010000 3
b1010000 y
b11110 )
b11110 2
b11110 x
1s
0r
b10001100 (
b10001100 1
b10001100 q
1t
b1011010 '
b1011010 0
b1011010 p
b101000 &
b101000 /
b101000 o
1j
0i
b10010110 %
b10010110 .
b10010110 h
b1100100 $
b1100100 -
b1100100 g
1k
b110010 #
b110010 ,
b110010 f
#550000
b10010 !
b10010 A
b10010 R
b11001 Q
b1000 S
b10100 c
b1111 d
0O
b1100 5
b1100 L
b1100 e
b10010 Z
b1100 9
b1100 M
b1100 [
b110 I
b1001 =
b1001 H
b1001 K
b11 J
b1010000 :
b1010000 T
b1010000 !"
b10000010 >
b10000010 ]
b10000010 ~
b11110 6
b11110 B
b11110 ""
b1011010 ;
b1011010 U
b1011010 v
0a
b10001100 ?
b10001100 ^
b10001100 u
0F
b101000 7
b101000 C
b101000 w
b1100100 <
b1100100 V
b1100100 m
b10010110 @
b10010110 _
b10010110 l
1E
0G
b110010 8
b110010 D
b110010 n
1"
#600000
0"
0|
1{
b0 +
b0 4
b0 z
b110010 *
b110010 3
b110010 y
0}
b1100100 )
b1100100 2
b1100100 x
b10010110 (
b10010110 1
b10010110 q
0s
b10100000 '
b10100000 0
b10100000 p
0t
1r
b10101010 &
b10101010 /
b10101010 o
b10110100 %
b10110100 .
b10110100 h
0j
b11001000 $
b11001000 -
b11001000 g
0k
1i
b11111111 #
b11111111 ,
b11111111 f
#650000
b11111111 @
b11111111 _
b11111111 l
b11001000 <
b11001000 V
b11001000 m
b10110100 8
b10110100 D
b10110100 n
0b
b10101010 ?
b10101010 ^
b10101010 u
0Y
b10100000 ;
b10100000 U
b10100000 v
0G
b10010110 7
b10010110 C
b10010110 w
b1100100 >
b1100100 ]
b1100100 ~
b110010 :
b110010 T
b110010 !"
b0 6
b0 B
b0 ""
b110010 =
b110010 H
b110010 K
b101000 I
b11110 J
b1100100 Z
b1011010 9
b1011010 M
b1011010 [
b1010000 \
b10010110 c
b10001100 d
1O
b10000010 5
b10000010 L
b10000010 e
b1100 !
b1100 A
b1100 R
b1100 Q
b1001 S
1"
#700000
0"
b10 +
b10 4
b10 z
b100 *
b100 3
b100 y
0}
b1000 )
b1000 2
b1000 x
b100000 (
b100000 1
b100000 q
0s
b1000000 '
b1000000 0
b1000000 p
0t
1r
b10000000 &
b10000000 /
b10000000 o
b10000 %
b10000 .
b10000 h
0j
b100000 $
b100000 -
b100000 g
0k
1i
b1000000 #
b1000000 ,
b1000000 f
#750000
b1011010 !
b1011010 A
b1011010 R
b10000010 Q
b110010 S
b11111111 c
b10101010 d
b1100100 5
b1100100 L
b1100100 e
b11001000 Z
0O
b10100000 9
b10100000 M
b10100000 [
b110010 \
0P
1N
b10110100 =
b10110100 H
b10110100 K
b10010110 I
b0 J
b1000 >
b1000 ]
b1000 ~
b100 :
b100 T
b100 !"
b10 6
b10 B
b10 ""
b10000000 ?
b10000000 ^
b10000000 u
b1000000 ;
b1000000 U
b1000000 v
b100000 7
b100000 C
b100000 w
1`
1b
b1000000 @
b1000000 _
b1000000 l
1W
1Y
b100000 <
b100000 V
b100000 m
1G
b10000 8
b10000 D
b10000 n
1"
#800000
0"
0{
b1101111 +
b1101111 4
b1101111 z
1}
b11011110 *
b11011110 3
b11011110 y
b1101111 )
b1101111 2
b1101111 x
1s
0r
b11011110 (
b11011110 1
b11011110 q
b1101111 '
b1101111 0
b1101111 p
b11011110 &
b11011110 /
b11011110 o
1j
0i
b11011110 %
b11011110 .
b11011110 h
b1101111 $
b1101111 -
b1101111 g
b1101111 #
b1101111 ,
b1101111 f
#850000
0b
b11011110 @
b11011110 _
b11011110 l
b1101111 <
b1101111 V
b1101111 m
0G
b1101111 8
b1101111 D
b1101111 n
b11011110 ?
b11011110 ^
b11011110 u
b11011110 ;
b11011110 U
b11011110 v
b1101111 7
b1101111 C
b1101111 w
0W
0X
b1101111 :
b1101111 T
b1101111 !"
0`
0a
b11011110 >
b11011110 ]
b11011110 ~
0E
0F
b1101111 6
b1101111 B
b1101111 ""
b100000 =
b100000 H
b100000 K
b10000 I
b10 J
b1000000 Z
b100000 9
b100000 M
b100000 [
b100 \
b10000000 c
b1000000 d
b1000 5
b1000 L
b1000 e
b10110100 Q
b10100000 !
b10100000 A
b10100000 R
b1100100 S
1"
#900000
0"
1{
b100011 +
b100011 4
b100011 z
0|
b1000001 *
b1000001 3
b1000001 y
b110111 )
b110111 2
b110111 x
b1010101 (
b1010101 1
b1010101 q
b11001 '
b11001 0
b11001 p
0t
b1001011 &
b1001011 /
b1001011 o
0j
b101101 %
b101101 .
b101101 h
b1011111 $
b1011111 -
b1011111 g
1k
b101 #
b101 ,
b101 f
#950000
b100000 Q
b100000 !
b100000 A
b100000 R
b1000 S
b11011110 c
b11011110 d
0N
1O
b11011110 5
b11011110 L
b11011110 e
b1101111 9
b1101111 M
b1101111 [
b11011110 Z
b1101111 \
b1101111 =
b1101111 H
b1101111 K
b1101111 I
b1101111 J
1`
b1000001 >
b1000001 ]
b1000001 ~
b110111 :
b110111 T
b110111 !"
b100011 6
b100011 B
b100011 ""
0a
b1010101 ?
b1010101 ^
b1010101 u
0X
b1001011 ;
b1001011 U
b1001011 v
1F
b11001 7
b11001 C
b11001 w
b101101 <
b101101 V
b101101 m
0b
b1011111 @
b1011111 _
b1011111 l
1G
b101 8
b101 D
b101 n
1"
#1000000
0"
#1050000
b11001 I
1P
b100011 =
b100011 H
b100011 K
b101 J
b110111 9
b110111 M
b110111 [
b1001011 Z
b101101 \
b1011111 c
b1010101 d
0N
1O
b1000001 5
b1000001 L
b1000001 e
b11011110 Q
b1101111 !
b1101111 A
b1101111 R
b1101111 S
1"
#1100000
0"
#1150000
b110111 !
b110111 A
b110111 R
b1000001 Q
b100011 S
1"
